{"date":"20250822","timestamp":"2026-05-09T19:56:17.147049","market":{"加權指數":null,"漲跌幅":null},"sectors":{"光通訊":{"avg_ret_20d":4.0,"avg_rsi":52.1,"avg_sharpe":-2.67,"hot_count":0,"buy_count":1,"qualified_count":0,"stocks":[{"id":"4979","name":"華星光","price":192.0,"rsi":51.6,"ret_20d":-0.3,"signal":"HOLD","cv_sharpe":0.87,"cv_win_rate":0.5333,"news":[],"chip":{"date":"2025-08-22","合計":0}},{"id":"3450","name":"聯鈞","price":188.5,"rsi":45.3,"ret_20d":-8.0,"signal":"BUY","cv_sharpe":2.72,"cv_win_rate":0.3278,"news":[],"chip":{"date":"2025-08-22","合計":0}},{"id":"3665","name":"貿聯-KY","price":942.0,"rsi":63.6,"ret_20d":13.1,"signal":"HOLD","cv_sharpe":6.27,"cv_win_rate":0.6111,"news":[],"chip":{"date":"2025-08-22","合計":0}},{"id":"3105","name":"穩懋","price":90.3,"rsi":58.5,"ret_20d":1.6,"signal":"HOLD","cv_sharpe":-0.75,"cv_win_rate":0.4762,"news":[],"chip":{"date":"2025-08-22","合計":0}},{"id":"8086","name":"宏捷科","price":107.0,"rsi":55.9,"ret_20d":11.9,"signal":"HOLD","cv_sharpe":-2.34,"cv_win_rate":0.2722,"news":[],"chip":{"date":"2025-08-22","合計":0}},{"id":"2455","name":"全新","price":142.5,"rsi":43.5,"ret_20d":-2.7,"signal":"SELL","cv_sharpe":3.02,"cv_win_rate":0.3889,"news":[],"chip":{"date":"2025-08-22","合計":0}},{"id":"4906","name":"正文","price":23.7,"rsi":40.9,"ret_20d":-2.1,"signal":"HOLD","cv_sharpe":-4.72,"cv_win_rate":0.3056,"news":[],"chip":{"date":"2025-08-22","合計":0}},{"id":"2345","name":"智邦","price":940.0,"rsi":57.7,"ret_20d":18.5,"signal":"HOLD","cv_sharpe":7.55,"cv_win_rate":0.6667,"news":[],"chip":{"date":"2025-08-22","合計":0}}]},"記憶體":{"avg_ret_20d":4.71,"avg_rsi":62.6,"avg_sharpe":-5.39,"hot_count":1,"buy_count":1,"qualified_count":0,"stocks":[{"id":"2408","name":"南亞科","price":45.35,"rsi":54.4,"ret_20d":4.9,"signal":"HOLD","cv_sharpe":6.2,"cv_win_rate":0.6667,"news":[],"chip":{"date":"2025-08-22","合計":0}},{"id":"2337","name":"旺宏","price":19.7,"rsi":64.4,"ret_20d":-2.0,"signal":"BUY","cv_sharpe":3.7,"cv_win_rate":0.6389,"news":[],"chip":{"date":"2025-08-22","合計":0}},{"id":"2344","name":"華邦電","price":18.2,"rsi":56.4,"ret_20d":4.3,"signal":"HOLD","cv_sharpe":7.83,"cv_win_rate":0.8333,"news":[],"chip":{"date":"2025-08-22","合計":0}},{"id":"3006","name":"晶豪科","price":54.7,"rsi":69.8,"ret_20d":6.0,"signal":"HOLD","cv_sharpe":-3.76,"cv_win_rate":0.3333,"news":[],"chip":{"date":"2025-08-22","合計":0}},{"id":"2451","name":"創見","price":97.2,"rsi":55.5,"ret_20d":8.1,"signal":"HOLD","cv_sharpe":5.44,"cv_win_rate":0.8889,"news":[],"chip":{"date":"2025-08-22","合計":0}},{"id":"5289","name":"宜鼎","price":242.5,"rsi":62.6,"ret_20d":7.8,"signal":"HOLD","cv_sharpe":2.06,"cv_win_rate":0.4167,"news":[],"chip":{"date":"2025-08-22","合計":0}},{"id":"3205","name":"十銓","price":50.9,"rsi":75.0,"ret_20d":3.9,"signal":"HOLD","cv_sharpe":-0.47,"cv_win_rate":0.3,"news":[],"chip":{"date":"2025-08-22","合計":0}}]},"AI伺服器":{"avg_ret_20d":-2.78,"avg_rsi":36.3,"avg_sharpe":-0.25,"hot_count":1,"buy_count":0,"qualified_count":0,"stocks":[{"id":"2317","name":"鴻海","price":202.5,"rsi":72.3,"ret_20d":16.0,"signal":"HOLD","cv_sharpe":-3.91,"cv_win_rate":0.15,"news":[],"chip":{"date":"2025-08-22","合計":0}},{"id":"2382","name":"廣達","price":258.5,"rsi":22.9,"ret_20d":-3.7,"signal":"SELL","cv_sharpe":0.63,"cv_win_rate":0.5056,"news":[],"chip":{"date":"2025-08-22","合計":0}},{"id":"3231","name":"緯創","price":112.0,"rsi":36.4,"ret_20d":-3.9,"signal":"SELL","cv_sharpe":-3.62,"cv_win_rate":0.3111,"news":[],"chip":{"date":"2025-08-22","合計":0}},{"id":"2376","name":"技嘉","price":271.0,"rsi":47.6,"ret_20d":-5.7,"signal":"SELL","cv_sharpe":-4.9,"cv_win_rate":0.2,"news":[],"chip":{"date":"2025-08-22","合計":0}},{"id":"4938","name":"和碩","price":69.5,"rsi":14.6,"ret_20d":-14.2,"signal":"HOLD","cv_sharpe":-4.18,"cv_win_rate":0.4444,"news":[],"chip":{"date":"2025-08-22","合計":0}},{"id":"2357","name":"華碩","price":621.0,"rsi":23.8,"ret_20d":-5.2,"signal":"HOLD","cv_sharpe":4.84,"cv_win_rate":0.5556,"news":[],"chip":{"date":"2025-08-22","合計":0}}]},"封測":{"avg_ret_20d":5.01,"avg_rsi":50.8,"avg_sharpe":-2.79,"hot_count":1,"buy_count":0,"qualified_count":0,"stocks":[{"id":"3711","name":"日月光投控","price":143.5,"rsi":40.9,"ret_20d":-6.5,"signal":"HOLD","cv_sharpe":-0.02,"cv_win_rate":0.4333,"news":[],"chip":{"date":"2025-08-22","合計":0}},{"id":"2449","name":"京元電子","price":131.5,"rsi":63.0,"ret_20d":17.4,"signal":"HOLD","cv_sharpe":-0.41,"cv_win_rate":0.4667,"news":[],"chip":{"date":"2025-08-22","合計":0}},{"id":"6510","name":"精測","price":1135.0,"rsi":87.6,"ret_20d":38.2,"signal":"HOLD","cv_sharpe":0.79,"cv_win_rate":0.4222,"news":[],"chip":{"date":"2025-08-22","合計":0}},{"id":"2441","name":"超豐","price":60.7,"rsi":38.3,"ret_20d":0.0,"signal":"SELL","cv_sharpe":2.04,"cv_win_rate":0.6,"news":[],"chip":{"date":"2025-08-22","合計":0}},{"id":"6257","name":"矽格","price":77.4,"rsi":38.7,"ret_20d":-2.6,"signal":"SELL","cv_sharpe":1.16,"cv_win_rate":0.4556,"news":[],"chip":{"date":"2025-08-22","合計":0}},{"id":"6239","name":"力成","price":117.0,"rsi":36.6,"ret_20d":-16.4,"signal":"HOLD","cv_sharpe":5.45,"cv_win_rate":0.6667,"news":[],"chip":{"date":"2025-08-22","合計":0}}]},"光學":{"avg_ret_20d":-0.74,"avg_rsi":46.7,"avg_sharpe":0.0,"hot_count":0,"buy_count":1,"qualified_count":0,"stocks":[{"id":"3008","name":"大立光","price":2360.0,"rsi":46.7,"ret_20d":0.0,"signal":"SELL","cv_sharpe":-1.49,"cv_win_rate":0.3889,"news":[],"chip":{"date":"2025-08-22","合計":0}},{"id":"3406","name":"玉晶光","price":432.0,"rsi":46.6,"ret_20d":-1.5,"signal":"BUY","cv_sharpe":1.45,"cv_win_rate":0.6111,"news":[],"chip":{"date":"2025-08-22","合計":0}}]},"IC設計":{"avg_ret_20d":-1.1,"avg_rsi":44.2,"avg_sharpe":-2.07,"hot_count":0,"buy_count":2,"qualified_count":0,"stocks":[{"id":"2454","name":"聯發科","price":1365.0,"rsi":57.4,"ret_20d":-4.5,"signal":"BUY","cv_sharpe":1.77,"cv_win_rate":0.5222,"news":[],"chip":{"date":"2025-08-22","合計":0}},{"id":"3034","name":"聯詠","price":423.0,"rsi":15.0,"ret_20d":-14.4,"signal":"HOLD","cv_sharpe":-2.4,"cv_win_rate":0.2778,"news":[],"chip":{"date":"2025-08-22","合計":0}},{"id":"4966","name":"譜瑞-KY","price":778.0,"rsi":70.0,"ret_20d":30.3,"signal":"HOLD","cv_sharpe":-3.85,"cv_win_rate":0.2333,"news":[],"chip":{"date":"2025-08-22","合計":0}},{"id":"4919","name":"新唐","price":58.9,"rsi":27.7,"ret_20d":-16.1,"signal":"HOLD","cv_sharpe":-4.19,"cv_win_rate":0.3333,"news":[],"chip":{"date":"2025-08-22","合計":0}},{"id":"2388","name":"威盛","price":60.7,"rsi":50.7,"ret_20d":-0.8,"signal":"BUY","cv_sharpe":-6.3,"cv_win_rate":0.2222,"news":[],"chip":{"date":"2025-08-22","合計":0}}]},"車用電子":{"avg_ret_20d":2.66,"avg_rsi":59.1,"avg_sharpe":-11.03,"hot_count":0,"buy_count":0,"qualified_count":0,"stocks":[{"id":"3552","name":"同致","price":64.3,"rsi":61.2,"ret_20d":7.9,"signal":"HOLD","cv_sharpe":-10.89,"cv_win_rate":0.1667,"news":[],"chip":{"date":"2025-08-22","合計":0}},{"id":"1533","name":"車王電","price":29.9,"rsi":56.2,"ret_20d":-0.8,"signal":"SELL","cv_sharpe":-8.58,"cv_win_rate":0.0833,"news":[],"chip":{"date":"2025-08-22","合計":0}},{"id":"2243","name":"怡利電","price":11.05,"rsi":60.0,"ret_20d":0.9,"signal":"HOLD","cv_sharpe":5.01,"cv_win_rate":0.6667,"news":[],"chip":{"date":"2025-08-22","合計":0}}]},"綠能環保":{"avg_ret_20d":3.31,"avg_rsi":56.1,"avg_sharpe":0.0,"hot_count":0,"buy_count":0,"qualified_count":0,"stocks":[{"id":"5292","name":"華懋","price":156.0,"rsi":56.1,"ret_20d":3.3,"signal":"HOLD","cv_sharpe":2.31,"cv_win_rate":0.6667,"news":[],"chip":{"date":"2025-08-22","合計":0}}]}},"strong_sectors":["光通訊","記憶體","封測","綠能環保"],"weak_sectors":[],"qualified":[],"alerts":[{"sector":"記憶體","id":"3205","name":"十銓","type":"RSI過熱","detail":"RSI=75.0"},{"sector":"AI伺服器","id":"2317","name":"鴻海","type":"RSI過熱","detail":"RSI=72.3"},{"sector":"封測","id":"6510","name":"精測","type":"RSI過熱","detail":"RSI=87.6"}],"chart_path":"daily_reports\\20250822\\01_sector_strength.png"}