{
  "date": "20260617",
  "timestamp": "2026-06-17T13:27:13.208549",
  "market": {
    "加權指數": 45877.39,
    "漲跌幅": 0.14887842373985893,
    "櫃買指數": 433.34,
    "櫃買漲跌幅": 0.7158462325105713
  },
  "sectors": {
    "光通訊": {
      "avg_ret_20d": 10.68,
      "avg_rsi": 57.9,
      "avg_sharpe": 0.83,
      "stocks": [
        {
          "id": "4979",
          "name": "華星光",
          "price": 546.0,
          "rsi": 48.9,
          "rsi10": 46.2,
          "ret_20d": -2.8,
          "signal": "HOLD",
          "cv_sharpe": -0.39,
          "cv_win_rate": 0.33,
          "news": [],
          "chip": {
            "date": "2026-06-17",
            "外資": -907262,
            "投信": -398000,
            "自營": -61637,
            "合計": -1366899
          },
          "target_short": 700.9,
          "target_mid": 464.1,
          "target_long": 609.7,
          "atr14": 46.34,
          "stop_loss": 453.3,
          "broker": null,
          "main_force": null
        },
        {
          "id": "3450",
          "name": "聯鈞",
          "price": 514.0,
          "rsi": 61.2,
          "rsi10": 57.5,
          "ret_20d": 24.3,
          "signal": "SELL",
          "cv_sharpe": -4.34,
          "cv_win_rate": 0.17,
          "news": [],
          "chip": {
            "date": "2026-06-17",
            "外資": -584240,
            "投信": 0,
            "自營": 1808,
            "合計": -582432
          },
          "target_short": 560.4,
          "target_mid": 436.9,
          "target_long": 554.1,
          "atr14": 40.99,
          "stop_loss": 432.0,
          "broker": null,
          "main_force": null
        },
        {
          "id": "3665",
          "name": "貿聯-KY",
          "price": 2090.0,
          "rsi": 51.9,
          "rsi10": 50.2,
          "ret_20d": 6.4,
          "signal": "BUY",
          "cv_sharpe": 2.7,
          "cv_win_rate": 0.39,
          "news": [],
          "chip": {
            "date": "2026-06-17",
            "外資": 78071,
            "投信": -912143,
            "自營": -26309,
            "合計": -860381
          },
          "target_short": 3067.2,
          "target_mid": 1815.5,
          "target_long": 2426.4,
          "atr14": 372.9,
          "stop_loss": 1344.2,
          "broker": null,
          "main_force": null
        },
        {
          "id": "3105",
          "name": "穩懋",
          "price": 519.0,
          "rsi": 62.2,
          "rsi10": 55.5,
          "ret_20d": 16.2,
          "signal": "HOLD",
          "cv_sharpe": 4.23,
          "cv_win_rate": 0.5,
          "news": [],
          "chip": {
            "date": "2026-06-17",
            "外資": 2602133,
            "投信": -570000,
            "自營": -44709,
            "合計": 1987424
          },
          "target_short": 567.6,
          "target_mid": 641.4,
          "target_long": 640.0,
          "atr14": 40.21,
          "stop_loss": 438.6,
          "broker": null,
          "main_force": null
        },
        {
          "id": "8086",
          "name": "宏捷科",
          "price": 162.5,
          "rsi": 66.2,
          "rsi10": 56.8,
          "ret_20d": 12.5,
          "signal": "HOLD",
          "cv_sharpe": 2.34,
          "cv_win_rate": 0.5,
          "news": [],
          "chip": {
            "date": "2026-06-17",
            "外資": 223176,
            "投信": 0,
            "自營": -42832,
            "合計": 180344
          },
          "target_short": 178.5,
          "target_mid": 220.4,
          "target_long": 208.4,
          "atr14": 9.64,
          "stop_loss": 143.2,
          "broker": null,
          "main_force": null
        },
        {
          "id": "2455",
          "name": "全新",
          "price": 428.0,
          "rsi": 68.9,
          "rsi10": 59.9,
          "ret_20d": 6.9,
          "signal": "HOLD",
          "cv_sharpe": 4.3,
          "cv_win_rate": 0.67,
          "news": [],
          "chip": {
            "date": "2026-06-17",
            "外資": 1812047,
            "投信": 790000,
            "自營": 503625,
            "合計": 3105672
          },
          "target_short": 458.6,
          "target_mid": 363.8,
          "target_long": 459.8,
          "atr14": 30.21,
          "stop_loss": 367.6,
          "broker": null,
          "main_force": null
        },
        {
          "id": "4906",
          "name": "正文",
          "price": 43.65,
          "rsi": 44.8,
          "rsi10": 48.1,
          "ret_20d": 16.1,
          "signal": "HOLD",
          "cv_sharpe": 0.84,
          "cv_win_rate": 0.61,
          "news": [],
          "chip": {
            "date": "2026-06-17",
            "外資": 118328,
            "投信": 0,
            "自營": 55160,
            "合計": 173488
          },
          "target_short": 53.7,
          "target_mid": 37.1,
          "target_long": 49.2,
          "atr14": 2.99,
          "stop_loss": 37.7,
          "broker": null,
          "main_force": null
        },
        {
          "id": "2345",
          "name": "智邦",
          "price": 2495.0,
          "rsi": 58.9,
          "rsi10": 53.9,
          "ret_20d": 5.9,
          "signal": "HOLD",
          "cv_sharpe": -3.05,
          "cv_win_rate": 0.28,
          "news": [],
          "chip": {
            "date": "2026-06-17",
            "外資": 104645,
            "投信": -4433,
            "自營": -179066,
            "合計": -78854
          },
          "target_short": 2646.9,
          "target_mid": 2120.8,
          "target_long": 2675.1,
          "atr14": 155.44,
          "stop_loss": 2184.1,
          "broker": null,
          "main_force": null
        }
      ],
      "hot_count": 0,
      "buy_count": 1,
      "qualified_count": 4
    },
    "記憶體": {
      "avg_ret_20d": 18.3,
      "avg_rsi": 55.6,
      "avg_sharpe": 4.05,
      "stocks": [
        {
          "id": "2408",
          "name": "南亞科",
          "price": 437.0,
          "rsi": 78.1,
          "rsi10": 69.8,
          "ret_20d": 58.9,
          "signal": "HOLD",
          "cv_sharpe": 10.17,
          "cv_win_rate": 0.89,
          "news": [],
          "chip": {
            "date": "2026-06-17",
            "外資": 4145978,
            "投信": 2241034,
            "自營": 646365,
            "合計": 7033377
          },
          "target_short": 447.0,
          "target_mid": 655.5,
          "target_long": 578.8,
          "atr14": 28.31,
          "stop_loss": 380.4,
          "broker": null,
          "main_force": null
        },
        {
          "id": "2337",
          "name": "旺宏",
          "price": 161.5,
          "rsi": 61.6,
          "rsi10": 55.9,
          "ret_20d": 14.5,
          "signal": "HOLD",
          "cv_sharpe": 3.11,
          "cv_win_rate": 0.5,
          "news": [],
          "chip": {
            "date": "2026-06-17",
            "外資": -15803449,
            "投信": -593000,
            "自營": 122840,
            "合計": -16273609
          },
          "target_short": 176.2,
          "target_mid": 137.3,
          "target_long": 177.4,
          "atr14": 11.08,
          "stop_loss": 139.3,
          "broker": null,
          "main_force": null
        },
        {
          "id": "2344",
          "name": "華邦電",
          "price": 199.0,
          "rsi": 80.6,
          "rsi10": 72.7,
          "ret_20d": 72.3,
          "signal": "HOLD",
          "cv_sharpe": 8.71,
          "cv_win_rate": 1.0,
          "news": [],
          "chip": {
            "date": "2026-06-17",
            "外資": -8995425,
            "投信": 1401595,
            "自營": 2078800,
            "合計": -5515030
          },
          "target_short": 207.3,
          "target_mid": 298.5,
          "target_long": 264.3,
          "atr14": 12.74,
          "stop_loss": 173.5,
          "broker": null,
          "main_force": null
        },
        {
          "id": "3006",
          "name": "晶豪科",
          "price": 225.0,
          "rsi": 55.5,
          "rsi10": 51.0,
          "ret_20d": 1.1,
          "signal": "HOLD",
          "cv_sharpe": 4.68,
          "cv_win_rate": 0.67,
          "news": [],
          "chip": {
            "date": "2026-06-17",
            "外資": 249713,
            "投信": 0,
            "自營": -658978,
            "合計": -409265
          },
          "target_short": 266.4,
          "target_mid": 259.6,
          "target_long": 271.2,
          "atr14": 16.72,
          "stop_loss": 191.6,
          "broker": null,
          "main_force": null
        },
        {
          "id": "2451",
          "name": "創見",
          "price": 311.0,
          "rsi": 49.0,
          "rsi10": 47.9,
          "ret_20d": 0.5,
          "signal": "HOLD",
          "cv_sharpe": 5.26,
          "cv_win_rate": 0.67,
          "news": [],
          "chip": {
            "date": "2026-06-17",
            "外資": -2420894,
            "投信": 454000,
            "自營": -33131,
            "合計": -2000025
          },
          "target_short": 365.5,
          "target_mid": 466.5,
          "target_long": 396.6,
          "atr14": 19.22,
          "stop_loss": 272.6,
          "broker": null,
          "main_force": null
        },
        {
          "id": "5289",
          "name": "宜鼎",
          "price": 1855.0,
          "rsi": 49.9,
          "rsi10": 53.3,
          "ret_20d": 10.7,
          "signal": "HOLD",
          "cv_sharpe": 4.93,
          "cv_win_rate": 0.72,
          "news": [],
          "chip": {
            "date": "2026-06-17",
            "外資": -1446248,
            "投信": 9000,
            "自營": 26606,
            "合計": -1410642
          },
          "target_short": 2004.7,
          "target_mid": 2435.2,
          "target_long": 2302.1,
          "atr14": 137.23,
          "stop_loss": 1580.5,
          "broker": null,
          "main_force": null
        },
        {
          "id": "3205",
          "name": "十銓",
          "price": 52.8,
          "rsi": 37.2,
          "rsi10": 43.0,
          "ret_20d": -2.0,
          "signal": "SELL",
          "cv_sharpe": -10.22,
          "cv_win_rate": 0.17,
          "news": [],
          "chip": {
            "date": "2026-06-17",
            "外資": -23000,
            "投信": 0,
            "自營": -1,
            "合計": -23001
          },
          "target_short": 56.3,
          "target_mid": 50.7,
          "target_long": 57.7,
          "atr14": 1.99,
          "stop_loss": 48.8,
          "broker": null,
          "main_force": null
        },
        {
          "id": "3260",
          "name": "威剛",
          "price": 416.0,
          "rsi": 50.6,
          "rsi10": 49.0,
          "ret_20d": 2.6,
          "signal": "HOLD",
          "cv_sharpe": 3.51,
          "cv_win_rate": 0.83,
          "news": [],
          "chip": {
            "date": "2026-06-17",
            "外資": 779978,
            "投信": -689000,
            "自營": -363223,
            "合計": -272245
          },
          "target_short": 461.5,
          "target_mid": 624.0,
          "target_long": 522.1,
          "atr14": 25.2,
          "stop_loss": 365.6,
          "broker": null,
          "main_force": null
        },
        {
          "id": "6770",
          "name": "力積電",
          "price": 70.2,
          "rsi": 47.2,
          "rsi10": 49.1,
          "ret_20d": 21.5,
          "signal": "HOLD",
          "cv_sharpe": 1.2,
          "cv_win_rate": 0.39,
          "news": [],
          "chip": {
            "date": "2026-06-17",
            "外資": -31701807,
            "投信": 0,
            "自營": 1040487,
            "合計": -30661320
          },
          "target_short": 90.6,
          "target_mid": 64.4,
          "target_long": 80.4,
          "atr14": 5.16,
          "stop_loss": 59.9,
          "broker": null,
          "main_force": null
        },
        {
          "id": "8299",
          "name": "群聯",
          "price": 2330.0,
          "rsi": 46.6,
          "rsi10": 46.8,
          "ret_20d": 2.9,
          "signal": "HOLD",
          "cv_sharpe": 9.12,
          "cv_win_rate": 1.0,
          "news": [],
          "chip": {
            "date": "2026-06-17",
            "外資": -762047,
            "投信": -6176,
            "自營": -325355,
            "合計": -1093578
          },
          "target_short": 2798.0,
          "target_mid": 3495.0,
          "target_long": 3097.3,
          "atr14": 169.84,
          "stop_loss": 1990.3,
          "broker": null,
          "main_force": null
        }
      ],
      "hot_count": 2,
      "buy_count": 0,
      "qualified_count": 8
    },
    "AI伺服器": {
      "avg_ret_20d": 18.83,
      "avg_rsi": 45.7,
      "avg_sharpe": 0.7,
      "stocks": [
        {
          "id": "2317",
          "name": "鴻海",
          "price": 272.0,
          "rsi": 53.6,
          "rsi10": 53.0,
          "ret_20d": 13.3,
          "signal": "HOLD",
          "cv_sharpe": -1.46,
          "cv_win_rate": 0.33,
          "news": [],
          "chip": {
            "date": "2026-06-17",
            "外資": -7229697,
            "投信": -595574,
            "自營": -585489,
            "合計": -8410760
          },
          "target_short": 306.8,
          "target_mid": 231.2,
          "target_long": 283.7,
          "atr14": 11.58,
          "stop_loss": 248.8,
          "broker": null,
          "main_force": null
        },
        {
          "id": "2382",
          "name": "廣達",
          "price": 374.0,
          "rsi": 53.9,
          "rsi10": 56.6,
          "ret_20d": 29.0,
          "signal": "HOLD",
          "cv_sharpe": 3.6,
          "cv_win_rate": 0.64,
          "news": [],
          "chip": {
            "date": "2026-06-17",
            "外資": 1704196,
            "投信": 959179,
            "自營": -541743,
            "合計": 2121632
          },
          "target_short": 428.9,
          "target_mid": 317.9,
          "target_long": 390.7,
          "atr14": 18.7,
          "stop_loss": 336.6,
          "broker": null,
          "main_force": null
        },
        {
          "id": "3231",
          "name": "緯創",
          "price": 162.5,
          "rsi": 53.2,
          "rsi10": 53.4,
          "ret_20d": 22.6,
          "signal": "SELL",
          "cv_sharpe": 7.63,
          "cv_win_rate": 0.83,
          "news": [],
          "chip": {
            "date": "2026-06-17",
            "外資": -9767732,
            "投信": 1260864,
            "自營": 265355,
            "合計": -8241513
          },
          "target_short": 190.4,
          "target_mid": 176.2,
          "target_long": 184.1,
          "atr14": 8.19,
          "stop_loss": 146.1,
          "broker": null,
          "main_force": null
        },
        {
          "id": "2376",
          "name": "技嘉",
          "price": 347.5,
          "rsi": 45.0,
          "rsi10": 50.6,
          "ret_20d": 15.1,
          "signal": "SELL",
          "cv_sharpe": -4.58,
          "cv_win_rate": 0.17,
          "news": [],
          "chip": {
            "date": "2026-06-17",
            "外資": -391075,
            "投信": -326236,
            "自營": -40381,
            "合計": -757692
          },
          "target_short": 397.4,
          "target_mid": 344.5,
          "target_long": 378.8,
          "atr14": 16.22,
          "stop_loss": 315.1,
          "broker": null,
          "main_force": null
        },
        {
          "id": "4938",
          "name": "和碩",
          "price": 83.0,
          "rsi": 20.3,
          "rsi10": 36.2,
          "ret_20d": 7.5,
          "signal": "HOLD",
          "cv_sharpe": -2.39,
          "cv_win_rate": 0.4,
          "news": [],
          "chip": {
            "date": "2026-06-17",
            "外資": 2546955,
            "投信": -1428013,
            "自營": 510883,
            "合計": 1629825
          },
          "target_short": 102.7,
          "target_mid": 70.5,
          "target_long": 88.3,
          "atr14": 4.31,
          "stop_loss": 74.4,
          "broker": null,
          "main_force": null
        },
        {
          "id": "2357",
          "name": "華碩",
          "price": 803.0,
          "rsi": 48.4,
          "rsi10": 54.8,
          "ret_20d": 25.5,
          "signal": "SELL",
          "cv_sharpe": 1.4,
          "cv_win_rate": 0.5,
          "news": [],
          "chip": {
            "date": "2026-06-17",
            "外資": 488748,
            "投信": -208482,
            "自營": 826,
            "合計": 281092
          },
          "target_short": 957.4,
          "target_mid": 691.1,
          "target_long": 835.2,
          "atr14": 34.79,
          "stop_loss": 733.4,
          "broker": null,
          "main_force": null
        }
      ],
      "hot_count": 0,
      "buy_count": 0,
      "qualified_count": 3
    },
    "封測": {
      "avg_ret_20d": 15.05,
      "avg_rsi": 48.9,
      "avg_sharpe": 2.11,
      "stocks": [
        {
          "id": "3711",
          "name": "日月光投控",
          "price": 595.0,
          "rsi": 61.8,
          "rsi10": 56.8,
          "ret_20d": 25.0,
          "signal": "HOLD",
          "cv_sharpe": 1.99,
          "cv_win_rate": 0.5,
          "news": [],
          "chip": {
            "date": "2026-06-17",
            "外資": -846515,
            "投信": -2242330,
            "自營": -148221,
            "合計": -3237066
          },
          "target_short": 652.9,
          "target_mid": 505.8,
          "target_long": 642.3,
          "atr14": 34.24,
          "stop_loss": 526.5,
          "broker": null,
          "main_force": null
        },
        {
          "id": "2449",
          "name": "京元電子",
          "price": 280.5,
          "rsi": 39.4,
          "rsi10": 41.4,
          "ret_20d": 1.1,
          "signal": "HOLD",
          "cv_sharpe": 2.62,
          "cv_win_rate": 0.58,
          "news": [],
          "chip": {
            "date": "2026-06-17",
            "外資": -1029593,
            "投信": 4918,
            "自營": -104476,
            "合計": -1129151
          },
          "target_short": 342.8,
          "target_mid": 238.4,
          "target_long": 309.8,
          "atr14": 17.43,
          "stop_loss": 245.6,
          "broker": null,
          "main_force": null
        },
        {
          "id": "6510",
          "name": "精測",
          "price": 3540.0,
          "rsi": 56.9,
          "rsi10": 53.4,
          "ret_20d": 4.6,
          "signal": "BUY",
          "cv_sharpe": 5.73,
          "cv_win_rate": 0.72,
          "news": [],
          "chip": {
            "date": "2026-06-17",
            "外資": 51208,
            "投信": 19000,
            "自營": -76856,
            "合計": -6648
          },
          "target_short": 3664.7,
          "target_mid": 3009.0,
          "target_long": 3777.3,
          "atr14": 243.82,
          "stop_loss": 3052.4,
          "broker": null,
          "main_force": null
        },
        {
          "id": "2441",
          "name": "超豐",
          "price": 126.5,
          "rsi": 52.3,
          "rsi10": 54.8,
          "ret_20d": 23.4,
          "signal": "SELL",
          "cv_sharpe": 8.42,
          "cv_win_rate": 0.78,
          "news": [],
          "chip": {
            "date": "2026-06-17",
            "外資": 1482245,
            "投信": -1702000,
            "自營": 523498,
            "合計": 303743
          },
          "target_short": 146.6,
          "target_mid": 107.5,
          "target_long": 136.6,
          "atr14": 6.56,
          "stop_loss": 113.4,
          "broker": null,
          "main_force": null
        },
        {
          "id": "6257",
          "name": "矽格",
          "price": 214.0,
          "rsi": 47.2,
          "rsi10": 49.0,
          "ret_20d": 3.4,
          "signal": "HOLD",
          "cv_sharpe": 1.43,
          "cv_win_rate": 0.57,
          "news": [],
          "chip": {
            "date": "2026-06-17",
            "外資": -1862693,
            "投信": 248000,
            "自營": -45453,
            "合計": -1660146
          },
          "target_short": 240.7,
          "target_mid": 181.9,
          "target_long": 232.2,
          "atr14": 12.05,
          "stop_loss": 189.9,
          "broker": null,
          "main_force": null
        },
        {
          "id": "6239",
          "name": "力成",
          "price": 345.0,
          "rsi": 57.7,
          "rsi10": 58.1,
          "ret_20d": 47.1,
          "signal": "HOLD",
          "cv_sharpe": 7.47,
          "cv_win_rate": 0.67,
          "news": [],
          "chip": {
            "date": "2026-06-17",
            "外資": -5789066,
            "投信": -131000,
            "自營": 553494,
            "合計": -5366572
          },
          "target_short": 389.8,
          "target_mid": 293.2,
          "target_long": 374.7,
          "atr14": 25.64,
          "stop_loss": 293.7,
          "broker": null,
          "main_force": null
        },
        {
          "id": "8150",
          "name": "南茂",
          "price": 94.9,
          "rsi": 49.7,
          "rsi10": 52.2,
          "ret_20d": 27.6,
          "signal": "HOLD",
          "cv_sharpe": -4.14,
          "cv_win_rate": 0.5,
          "news": [],
          "chip": {
            "date": "2026-06-17",
            "外資": -1627710,
            "投信": -4000,
            "自營": -887714,
            "合計": -2519424
          },
          "target_short": 111.6,
          "target_mid": 119.2,
          "target_long": 119.3,
          "atr14": 7.88,
          "stop_loss": 79.1,
          "broker": null,
          "main_force": null
        },
        {
          "id": "6147",
          "name": "頎邦",
          "price": 229.5,
          "rsi": 38.9,
          "rsi10": 45.7,
          "ret_20d": 6.5,
          "signal": "HOLD",
          "cv_sharpe": 0.49,
          "cv_win_rate": 0.5,
          "news": [],
          "chip": {
            "date": "2026-06-17",
            "外資": 1502213,
            "投信": 547378,
            "自營": 323093,
            "合計": 2372684
          },
          "target_short": 303.9,
          "target_mid": 195.1,
          "target_long": 258.1,
          "atr14": 20.38,
          "stop_loss": 188.7,
          "broker": null,
          "main_force": null
        },
        {
          "id": "3264",
          "name": "欣銓",
          "price": 211.5,
          "rsi": 35.9,
          "rsi10": 43.4,
          "ret_20d": 2.4,
          "signal": "HOLD",
          "cv_sharpe": 9.02,
          "cv_win_rate": 0.89,
          "news": [],
          "chip": {
            "date": "2026-06-17",
            "外資": -1217059,
            "投信": -2811000,
            "自營": -152468,
            "合計": -4180527
          },
          "target_short": 242.1,
          "target_mid": 179.8,
          "target_long": 230.3,
          "atr14": 15.17,
          "stop_loss": 181.2,
          "broker": null,
          "main_force": null
        },
        {
          "id": "2369",
          "name": "菱生",
          "price": 34.5,
          "rsi": 53.8,
          "rsi10": 52.1,
          "ret_20d": 19.6,
          "signal": "HOLD",
          "cv_sharpe": -9.82,
          "cv_win_rate": 0.11,
          "news": [],
          "chip": {
            "date": "2026-06-17",
            "外資": -250202,
            "投信": 0,
            "自營": -206001,
            "合計": -456203
          },
          "target_short": 41.4,
          "target_mid": 29.3,
          "target_long": 38.6,
          "atr14": 2.19,
          "stop_loss": 30.1,
          "broker": null,
          "main_force": null
        },
        {
          "id": "2329",
          "name": "華泰",
          "price": 54.3,
          "rsi": 46.4,
          "rsi10": 45.6,
          "ret_20d": 5.6,
          "signal": "HOLD",
          "cv_sharpe": -4.13,
          "cv_win_rate": 0.17,
          "news": [],
          "chip": {
            "date": "2026-06-17",
            "外資": 311586,
            "投信": 0,
            "自營": -139279,
            "合計": 172307
          },
          "target_short": 62.1,
          "target_mid": 68.2,
          "target_long": 66.7,
          "atr14": 3.18,
          "stop_loss": 47.9,
          "broker": null,
          "main_force": null
        },
        {
          "id": "6271",
          "name": "同欣電",
          "price": 225.0,
          "rsi": 42.8,
          "rsi10": 48.4,
          "ret_20d": 20.0,
          "signal": "SELL",
          "cv_sharpe": 2.41,
          "cv_win_rate": 0.44,
          "news": [],
          "chip": {
            "date": "2026-06-17",
            "外資": 151893,
            "投信": 0,
            "自營": -174557,
            "合計": -22664
          },
          "target_short": 265.6,
          "target_mid": 191.2,
          "target_long": 246.6,
          "atr14": 15.0,
          "stop_loss": 195.0,
          "broker": null,
          "main_force": null
        },
        {
          "id": "2481",
          "name": "強茂",
          "price": 145.5,
          "rsi": 52.8,
          "rsi10": 53.3,
          "ret_20d": 9.4,
          "signal": "SELL",
          "cv_sharpe": 5.97,
          "cv_win_rate": 0.75,
          "news": [],
          "chip": {
            "date": "2026-06-17",
            "外資": 941020,
            "投信": -232000,
            "自營": -58951,
            "合計": 650069
          },
          "target_short": 166.2,
          "target_mid": 123.7,
          "target_long": 158.4,
          "atr14": 11.28,
          "stop_loss": 122.9,
          "broker": null,
          "main_force": null
        }
      ],
      "hot_count": 0,
      "buy_count": 1,
      "qualified_count": 10
    },
    "光學": {
      "avg_ret_20d": 46.03,
      "avg_rsi": 74.2,
      "avg_sharpe": -1.88,
      "stocks": [
        {
          "id": "3008",
          "name": "大立光",
          "price": 5145.0,
          "rsi": 87.2,
          "rsi10": 79.8,
          "ret_20d": 60.8,
          "signal": "HOLD",
          "cv_sharpe": -5.82,
          "cv_win_rate": 0.33,
          "news": [],
          "chip": {
            "date": "2026-06-17",
            "外資": 311668,
            "投信": 470834,
            "自營": -11556,
            "合計": 770946
          },
          "target_short": 4830.8,
          "target_mid": 4373.2,
          "target_long": 5390.9,
          "atr14": 289.74,
          "stop_loss": 4565.5,
          "broker": null,
          "main_force": null
        },
        {
          "id": "3406",
          "name": "玉晶光",
          "price": 722.0,
          "rsi": 61.2,
          "rsi10": 63.8,
          "ret_20d": 31.3,
          "signal": "HOLD",
          "cv_sharpe": 2.07,
          "cv_win_rate": 0.61,
          "news": [],
          "chip": {
            "date": "2026-06-17",
            "外資": -823503,
            "投信": -147000,
            "自營": -96832,
            "合計": -1067335
          },
          "target_short": 758.9,
          "target_mid": 613.7,
          "target_long": 749.2,
          "atr14": 46.71,
          "stop_loss": 628.6,
          "broker": null,
          "main_force": null
        }
      ],
      "hot_count": 1,
      "buy_count": 0,
      "qualified_count": 1
    },
    "IC設計": {
      "avg_ret_20d": 10.89,
      "avg_rsi": 61.6,
      "avg_sharpe": -2.3,
      "stocks": [
        {
          "id": "2454",
          "name": "聯發科",
          "price": 4460.0,
          "rsi": 57.8,
          "rsi10": 58.7,
          "ret_20d": 38.1,
          "signal": "HOLD",
          "cv_sharpe": 1.05,
          "cv_win_rate": 0.42,
          "news": [],
          "chip": {
            "date": "2026-06-17",
            "外資": -1051822,
            "投信": -363043,
            "自營": -19461,
            "合計": -1434326
          },
          "target_short": 4841.1,
          "target_mid": 3791.0,
          "target_long": 4803.8,
          "atr14": 296.89,
          "stop_loss": 3866.2,
          "broker": null,
          "main_force": null
        },
        {
          "id": "3034",
          "name": "聯詠",
          "price": 515.0,
          "rsi": 80.7,
          "rsi10": 68.7,
          "ret_20d": 9.0,
          "signal": "HOLD",
          "cv_sharpe": -6.3,
          "cv_win_rate": 0.28,
          "news": [],
          "chip": {
            "date": "2026-06-17",
            "外資": 1095755,
            "投信": -400368,
            "自營": 581630,
            "合計": 1277017
          },
          "target_short": 511.1,
          "target_mid": 437.8,
          "target_long": 526.8,
          "atr14": 16.95,
          "stop_loss": 481.1,
          "broker": null,
          "main_force": null
        },
        {
          "id": "4966",
          "name": "譜瑞-KY",
          "price": 675.0,
          "rsi": 39.9,
          "rsi10": 40.7,
          "ret_20d": -10.8,
          "signal": "HOLD",
          "cv_sharpe": -6.18,
          "cv_win_rate": 0.33,
          "news": [],
          "chip": {
            "date": "2026-06-17",
            "外資": 150327,
            "投信": -23000,
            "自營": 14551,
            "合計": 141878
          },
          "target_short": 910.5,
          "target_mid": 580.8,
          "target_long": 740.7,
          "atr14": 47.72,
          "stop_loss": 579.6,
          "broker": null,
          "main_force": null
        },
        {
          "id": "4919",
          "name": "新唐",
          "price": 187.5,
          "rsi": 56.1,
          "rsi10": 53.2,
          "ret_20d": 13.6,
          "signal": "HOLD",
          "cv_sharpe": -3.29,
          "cv_win_rate": 0.33,
          "news": [],
          "chip": {
            "date": "2026-06-17",
            "外資": -2419610,
            "投信": -47000,
            "自營": 726235,
            "合計": -1740375
          },
          "target_short": 223.8,
          "target_mid": 159.4,
          "target_long": 209.8,
          "atr14": 16.31,
          "stop_loss": 154.9,
          "broker": null,
          "main_force": null
        },
        {
          "id": "2388",
          "name": "威盛",
          "price": 75.2,
          "rsi": 70.0,
          "rsi10": 57.5,
          "ret_20d": -8.0,
          "signal": "HOLD",
          "cv_sharpe": -0.82,
          "cv_win_rate": 0.5,
          "news": [],
          "chip": {
            "date": "2026-06-17",
            "外資": 1905577,
            "投信": 0,
            "自營": 755911,
            "合計": 2661488
          },
          "target_short": 87.4,
          "target_mid": 75.4,
          "target_long": 86.7,
          "atr14": 4.74,
          "stop_loss": 65.7,
          "broker": null,
          "main_force": null
        },
        {
          "id": "2379",
          "name": "瑞昱",
          "price": 745.0,
          "rsi": 79.6,
          "rsi10": 72.1,
          "ret_20d": 31.4,
          "signal": "HOLD",
          "cv_sharpe": -0.35,
          "cv_win_rate": 0.5,
          "news": [],
          "chip": {
            "date": "2026-06-17",
            "外資": 571928,
            "投信": 149963,
            "自營": 278415,
            "合計": 1000306
          },
          "target_short": 708.5,
          "target_mid": 633.2,
          "target_long": 772.9,
          "atr14": 39.2,
          "stop_loss": 666.6,
          "broker": null,
          "main_force": null
        },
        {
          "id": "6415",
          "name": "矽力-KY",
          "price": 572.0,
          "rsi": 61.4,
          "rsi10": 56.4,
          "ret_20d": 12.8,
          "signal": "HOLD",
          "cv_sharpe": -2.05,
          "cv_win_rate": 0.33,
          "news": [],
          "chip": {
            "date": "2026-06-17",
            "外資": -2303444,
            "投信": 532000,
            "自營": -99788,
            "合計": -1871232
          },
          "target_short": 669.4,
          "target_mid": 486.2,
          "target_long": 625.8,
          "atr14": 40.78,
          "stop_loss": 490.4,
          "broker": null,
          "main_force": null
        },
        {
          "id": "5269",
          "name": "祥碩",
          "price": 1425.0,
          "rsi": 55.6,
          "rsi10": 50.0,
          "ret_20d": 2.9,
          "signal": "HOLD",
          "cv_sharpe": 0.61,
          "cv_win_rate": 0.5,
          "news": [],
          "chip": {
            "date": "2026-06-17",
            "外資": 46237,
            "投信": 15000,
            "自營": 57026,
            "合計": 118263
          },
          "target_short": 1624.3,
          "target_mid": 1628.7,
          "target_long": 1646.0,
          "atr14": 76.06,
          "stop_loss": 1272.9,
          "broker": null,
          "main_force": null
        },
        {
          "id": "2458",
          "name": "義隆",
          "price": 156.5,
          "rsi": 59.8,
          "rsi10": 53.4,
          "ret_20d": 2.3,
          "signal": "HOLD",
          "cv_sharpe": -0.27,
          "cv_win_rate": 0.33,
          "news": [],
          "chip": {
            "date": "2026-06-17",
            "外資": 897002,
            "投信": 111837,
            "自營": 25024,
            "合計": 1033863
          },
          "target_short": 172.5,
          "target_mid": 143.2,
          "target_long": 165.2,
          "atr14": 7.65,
          "stop_loss": 141.2,
          "broker": null,
          "main_force": null
        },
        {
          "id": "3058",
          "name": "聯陽",
          "price": 9.48,
          "rsi": 54.9,
          "rsi10": 55.5,
          "ret_20d": 17.6,
          "signal": "HOLD",
          "cv_sharpe": -5.45,
          "cv_win_rate": 0.17,
          "news": [],
          "chip": {
            "date": "2026-06-17",
            "外資": 220000,
            "投信": 0,
            "自營": 1000,
            "合計": 221000
          },
          "target_short": 10.6,
          "target_mid": 9.4,
          "target_long": 10.5,
          "atr14": 0.45,
          "stop_loss": 8.6,
          "broker": null,
          "main_force": null
        }
      ],
      "hot_count": 2,
      "buy_count": 0,
      "qualified_count": 2
    },
    "車用電子": {
      "avg_ret_20d": 40.66,
      "avg_rsi": 60.8,
      "avg_sharpe": -4.3,
      "stocks": [
        {
          "id": "3552",
          "name": "同致",
          "price": 50.3,
          "rsi": 48.1,
          "rsi10": 43.2,
          "ret_20d": -2.5,
          "signal": "HOLD",
          "cv_sharpe": -4.42,
          "cv_win_rate": 0.33,
          "news": [],
          "chip": {
            "date": "2026-06-17",
            "外資": 12039,
            "投信": 0,
            "自營": 9999,
            "合計": 22038
          },
          "target_short": 57.2,
          "target_mid": 54.8,
          "target_long": 59.5,
          "atr14": 1.86,
          "stop_loss": 46.6,
          "broker": null,
          "main_force": null
        },
        {
          "id": "1533",
          "name": "車王電",
          "price": 37.85,
          "rsi": 39.3,
          "rsi10": 49.3,
          "ret_20d": -0.4,
          "signal": "SELL",
          "cv_sharpe": -4.57,
          "cv_win_rate": 0.22,
          "news": [],
          "chip": {
            "date": "2026-06-17",
            "外資": -43030,
            "投信": 0,
            "自營": -2000,
            "合計": -45030
          },
          "target_short": 40.2,
          "target_mid": 56.8,
          "target_long": 49.4,
          "atr14": 1.57,
          "stop_loss": 34.7,
          "broker": null,
          "main_force": null
        },
        {
          "id": "2243",
          "name": "怡利電",
          "price": 47.0,
          "rsi": 95.1,
          "rsi10": 88.4,
          "ret_20d": 124.9,
          "signal": "HOLD",
          "cv_sharpe": -3.91,
          "cv_win_rate": 0.25,
          "news": [],
          "chip": {
            "date": "2026-06-17",
            "外資": 58050,
            "投信": 0,
            "自營": -21000,
            "合計": 37050
          },
          "target_short": 44.5,
          "target_mid": 68.7,
          "target_long": 58.7,
          "atr14": 2.58,
          "stop_loss": 41.8,
          "broker": null,
          "main_force": null
        }
      ],
      "hot_count": 1,
      "buy_count": 0,
      "qualified_count": 0
    },
    "綠能環保": {
      "avg_ret_20d": 1.8,
      "avg_rsi": 66.8,
      "avg_sharpe": -3.17,
      "stocks": [
        {
          "id": "5292",
          "name": "華懋",
          "price": 226.0,
          "rsi": 66.8,
          "rsi10": 56.6,
          "ret_20d": 1.8,
          "signal": "HOLD",
          "cv_sharpe": -3.17,
          "cv_win_rate": 0.5,
          "news": [],
          "chip": {
            "date": "2026-06-17",
            "外資": 2000,
            "投信": 0,
            "自營": 8081,
            "合計": 10081
          },
          "target_short": 235.8,
          "target_mid": 192.1,
          "target_long": 234.6,
          "atr14": 9.22,
          "stop_loss": 207.6,
          "broker": null,
          "main_force": null
        }
      ],
      "hot_count": 0,
      "buy_count": 0,
      "qualified_count": 0
    },
    "CoPoS封裝": {
      "avg_ret_20d": 6.5,
      "avg_rsi": 52.8,
      "avg_sharpe": 1.13,
      "stocks": [
        {
          "id": "6789",
          "name": "采鈺",
          "price": 494.0,
          "rsi": 52.4,
          "rsi10": 45.5,
          "ret_20d": -4.8,
          "signal": "HOLD",
          "cv_sharpe": 7.91,
          "cv_win_rate": 0.83,
          "news": [],
          "chip": {
            "date": "2026-06-17",
            "外資": 136349,
            "投信": -4000,
            "自營": 13130,
            "合計": 145479
          },
          "target_short": 579.5,
          "target_mid": 419.9,
          "target_long": 540.7,
          "atr14": 29.73,
          "stop_loss": 434.5,
          "broker": null,
          "main_force": null
        },
        {
          "id": "3535",
          "name": "晶彩科",
          "price": 134.5,
          "rsi": 64.7,
          "rsi10": 57.0,
          "ret_20d": 10.2,
          "signal": "SELL",
          "cv_sharpe": 8.08,
          "cv_win_rate": 0.75,
          "news": [],
          "chip": {
            "date": "2026-06-17",
            "外資": 189800,
            "投信": 0,
            "自營": 38000,
            "合計": 227800
          },
          "target_short": 139.4,
          "target_mid": 114.3,
          "target_long": 143.6,
          "atr14": 7.78,
          "stop_loss": 118.9,
          "broker": null,
          "main_force": null
        },
        {
          "id": "3680",
          "name": "家登",
          "price": 517.0,
          "rsi": 57.3,
          "rsi10": 49.2,
          "ret_20d": 2.2,
          "signal": "HOLD",
          "cv_sharpe": -5.29,
          "cv_win_rate": 0.17,
          "news": [],
          "chip": {
            "date": "2026-06-17",
            "外資": 1129,
            "投信": -33000,
            "自營": 38157,
            "合計": 6286
          },
          "target_short": 591.3,
          "target_mid": 454.2,
          "target_long": 568.8,
          "atr14": 33.19,
          "stop_loss": 450.6,
          "broker": null,
          "main_force": null
        },
        {
          "id": "6664",
          "name": "群翊",
          "price": 375.5,
          "rsi": 40.0,
          "rsi10": 37.4,
          "ret_20d": -4.3,
          "signal": "HOLD",
          "cv_sharpe": 0.08,
          "cv_win_rate": 0.42,
          "news": [],
          "chip": {
            "date": "2026-06-17",
            "外資": -45706,
            "投信": 0,
            "自營": 12335,
            "合計": -33371
          },
          "target_short": 471.6,
          "target_mid": 319.2,
          "target_long": 411.0,
          "atr14": 21.9,
          "stop_loss": 331.7,
          "broker": null,
          "main_force": null
        },
        {
          "id": "2467",
          "name": "志聖",
          "price": 585.0,
          "rsi": 57.8,
          "rsi10": 51.0,
          "ret_20d": 5.6,
          "signal": "HOLD",
          "cv_sharpe": 3.3,
          "cv_win_rate": 0.67,
          "news": [],
          "chip": {
            "date": "2026-06-17",
            "外資": 275939,
            "投信": 0,
            "自營": 5713,
            "合計": 281652
          },
          "target_short": 675.4,
          "target_mid": 497.2,
          "target_long": 638.2,
          "atr14": 38.78,
          "stop_loss": 507.4,
          "broker": null,
          "main_force": null
        },
        {
          "id": "7734",
          "name": "印能",
          "price": 3350.0,
          "rsi": 62.8,
          "rsi10": 53.5,
          "ret_20d": 0.1,
          "signal": "HOLD",
          "cv_sharpe": -3.92,
          "cv_win_rate": 0.33,
          "news": [],
          "chip": {
            "date": "2026-06-17",
            "外資": -2952,
            "投信": 12000,
            "自營": -11776,
            "合計": -2728
          },
          "target_short": 3844.6,
          "target_mid": 2847.5,
          "target_long": 3649.9,
          "atr14": 310.16,
          "stop_loss": 2729.7,
          "broker": null,
          "main_force": null
        },
        {
          "id": "5443",
          "name": "均豪",
          "price": 104.5,
          "rsi": 37.3,
          "rsi10": 35.9,
          "ret_20d": -10.3,
          "signal": "HOLD",
          "cv_sharpe": 4.9,
          "cv_win_rate": 0.8,
          "news": [],
          "chip": {
            "date": "2026-06-17",
            "外資": -32070,
            "投信": 0,
            "自營": 20891,
            "合計": -11179
          },
          "target_short": 136.8,
          "target_mid": 98.3,
          "target_long": 121.0,
          "atr14": 6.62,
          "stop_loss": 91.3,
          "broker": null,
          "main_force": null
        },
        {
          "id": "6640",
          "name": "均華",
          "price": 1085.0,
          "rsi": 36.4,
          "rsi10": 34.4,
          "ret_20d": -13.2,
          "signal": "HOLD",
          "cv_sharpe": -6.45,
          "cv_win_rate": 0.25,
          "news": [],
          "chip": {
            "date": "2026-06-17",
            "外資": -22985,
            "投信": -12000,
            "自營": 5612,
            "合計": -29373
          },
          "target_short": 1530.9,
          "target_mid": 922.2,
          "target_long": 1239.3,
          "atr14": 82.69,
          "stop_loss": 919.6,
          "broker": null,
          "main_force": null
        },
        {
          "id": "6187",
          "name": "萬潤",
          "price": 1155.0,
          "rsi": 64.5,
          "rsi10": 55.3,
          "ret_20d": 6.5,
          "signal": "HOLD",
          "cv_sharpe": -2.89,
          "cv_win_rate": 0.33,
          "news": [],
          "chip": {
            "date": "2026-06-17",
            "外資": 121002,
            "投信": -1000,
            "自營": -11000,
            "合計": 109002
          },
          "target_short": 1224.3,
          "target_mid": 981.8,
          "target_long": 1238.2,
          "atr14": 89.35,
          "stop_loss": 976.3,
          "broker": null,
          "main_force": null
        },
        {
          "id": "3131",
          "name": "弘塑",
          "price": 3245.0,
          "rsi": 55.6,
          "rsi10": 54.5,
          "ret_20d": 25.8,
          "signal": "HOLD",
          "cv_sharpe": -11.66,
          "cv_win_rate": 0.0,
          "news": [],
          "chip": {
            "date": "2026-06-17",
            "外資": -117089,
            "投信": 14000,
            "自營": 21281,
            "合計": -81808
          },
          "target_short": 3605.3,
          "target_mid": 2758.2,
          "target_long": 3511.8,
          "atr14": 211.62,
          "stop_loss": 2821.8,
          "broker": null,
          "main_force": null
        },
        {
          "id": "3583",
          "name": "辛耘",
          "price": 827.0,
          "rsi": 52.1,
          "rsi10": 48.5,
          "ret_20d": 0.1,
          "signal": "HOLD",
          "cv_sharpe": 9.71,
          "cv_win_rate": 1.0,
          "news": [],
          "chip": {
            "date": "2026-06-17",
            "外資": 135402,
            "投信": 0,
            "自營": -8418,
            "合計": 126984
          },
          "target_short": 923.4,
          "target_mid": 702.9,
          "target_long": 895.9,
          "atr14": 54.12,
          "stop_loss": 718.8,
          "broker": null,
          "main_force": null
        },
        {
          "id": "3711",
          "name": "日月光投控",
          "price": 595.0,
          "rsi": 61.8,
          "rsi10": 56.8,
          "ret_20d": 25.0,
          "signal": "HOLD",
          "cv_sharpe": 1.99,
          "cv_win_rate": 0.5,
          "news": [],
          "chip": {
            "date": "2026-06-17",
            "外資": -846515,
            "投信": -2242330,
            "自營": -148221,
            "合計": -3237066
          },
          "target_short": 652.9,
          "target_mid": 505.8,
          "target_long": 642.3,
          "atr14": 34.24,
          "stop_loss": 526.5,
          "broker": null,
          "main_force": null
        },
        {
          "id": "2449",
          "name": "京元電子",
          "price": 280.5,
          "rsi": 39.4,
          "rsi10": 41.4,
          "ret_20d": 1.1,
          "signal": "HOLD",
          "cv_sharpe": 2.62,
          "cv_win_rate": 0.58,
          "news": [],
          "chip": {
            "date": "2026-06-17",
            "外資": -1029593,
            "投信": 4918,
            "自營": -104476,
            "合計": -1129151
          },
          "target_short": 342.8,
          "target_mid": 238.4,
          "target_long": 309.8,
          "atr14": 17.43,
          "stop_loss": 245.6,
          "broker": null,
          "main_force": null
        },
        {
          "id": "6239",
          "name": "力成",
          "price": 345.0,
          "rsi": 57.7,
          "rsi10": 58.1,
          "ret_20d": 47.1,
          "signal": "HOLD",
          "cv_sharpe": 7.47,
          "cv_win_rate": 0.67,
          "news": [],
          "chip": {
            "date": "2026-06-17",
            "外資": -5789066,
            "投信": -131000,
            "自營": 553494,
            "合計": -5366572
          },
          "target_short": 389.8,
          "target_mid": 293.2,
          "target_long": 374.7,
          "atr14": 25.64,
          "stop_loss": 293.7,
          "broker": null,
          "main_force": null
        }
      ],
      "hot_count": 0,
      "buy_count": 0,
      "qualified_count": 8
    },
    "銅箔/CCL": {
      "avg_ret_20d": 17.65,
      "avg_rsi": 61.3,
      "avg_sharpe": 5.51,
      "stocks": [
        {
          "id": "8358",
          "name": "金居",
          "price": 640.0,
          "rsi": 68.8,
          "rsi10": 63.9,
          "ret_20d": 39.1,
          "signal": "HOLD",
          "cv_sharpe": 7.71,
          "cv_win_rate": 0.7,
          "news": [],
          "chip": {
            "date": "2026-06-17",
            "外資": 75970,
            "投信": -10000,
            "自營": 511676,
            "合計": 577646
          },
          "target_short": 672.5,
          "target_mid": 544.0,
          "target_long": 684.9,
          "atr14": 43.37,
          "stop_loss": 553.3,
          "broker": null,
          "main_force": null
        },
        {
          "id": "2383",
          "name": "台光電",
          "price": 5200.0,
          "rsi": 64.9,
          "rsi10": 59.4,
          "ret_20d": 18.3,
          "signal": "BUY",
          "cv_sharpe": 6.34,
          "cv_win_rate": 0.58,
          "news": [],
          "chip": {
            "date": "2026-06-17",
            "外資": 237842,
            "投信": -54289,
            "自營": -71166,
            "合計": 112387
          },
          "target_short": 5430.7,
          "target_mid": 4420.0,
          "target_long": 5558.1,
          "atr14": 329.57,
          "stop_loss": 4540.9,
          "broker": null,
          "main_force": null
        },
        {
          "id": "6213",
          "name": "聯茂",
          "price": 267.5,
          "rsi": 61.9,
          "rsi10": 54.3,
          "ret_20d": 13.1,
          "signal": "HOLD",
          "cv_sharpe": 1.83,
          "cv_win_rate": 0.5,
          "news": [],
          "chip": {
            "date": "2026-06-17",
            "外資": 3070019,
            "投信": 0,
            "自營": 199507,
            "合計": 3269526
          },
          "target_short": 286.8,
          "target_mid": 227.4,
          "target_long": 287.4,
          "atr14": 19.22,
          "stop_loss": 229.1,
          "broker": null,
          "main_force": null
        },
        {
          "id": "2368",
          "name": "金像電",
          "price": 1370.0,
          "rsi": 54.4,
          "rsi10": 52.2,
          "ret_20d": 10.9,
          "signal": "SELL",
          "cv_sharpe": 10.41,
          "cv_win_rate": 0.83,
          "news": [],
          "chip": {
            "date": "2026-06-17",
            "外資": 76666,
            "投信": -70163,
            "自營": 8139,
            "合計": 14642
          },
          "target_short": 1467.1,
          "target_mid": 1164.5,
          "target_long": 1471.6,
          "atr14": 100.67,
          "stop_loss": 1168.7,
          "broker": null,
          "main_force": null
        },
        {
          "id": "8046",
          "name": "南電",
          "price": 885.0,
          "rsi": 56.7,
          "rsi10": 53.2,
          "ret_20d": 6.8,
          "signal": "SELL",
          "cv_sharpe": 1.28,
          "cv_win_rate": 0.5,
          "news": [],
          "chip": {
            "date": "2026-06-17",
            "外資": -1637366,
            "投信": -2327000,
            "自營": 97141,
            "合計": -3867225
          },
          "target_short": 944.6,
          "target_mid": 924.2,
          "target_long": 1018.8,
          "atr14": 65.32,
          "stop_loss": 754.4,
          "broker": null,
          "main_force": null
        }
      ],
      "hot_count": 0,
      "buy_count": 1,
      "qualified_count": 5
    },
    "AI ASIC/IP": {
      "avg_ret_20d": -1.56,
      "avg_rsi": 56.1,
      "avg_sharpe": -3.43,
      "stocks": [
        {
          "id": "2330",
          "name": "台積電",
          "price": 2385.0,
          "rsi": 64.8,
          "rsi10": 60.5,
          "ret_20d": 9.2,
          "signal": "HOLD",
          "cv_sharpe": 0.69,
          "cv_win_rate": 0.67,
          "news": [],
          "chip": {
            "date": "2026-06-17",
            "外資": -6864860,
            "投信": -312313,
            "自營": 883192,
            "合計": -6293981
          },
          "target_short": 2439.7,
          "target_mid": 2027.2,
          "target_long": 2539.0,
          "atr14": 59.41,
          "stop_loss": 2266.2,
          "broker": null,
          "main_force": null
        },
        {
          "id": "3443",
          "name": "創意",
          "price": 5075.0,
          "rsi": 78.4,
          "rsi10": 64.1,
          "ret_20d": 10.2,
          "signal": "HOLD",
          "cv_sharpe": 2.9,
          "cv_win_rate": 0.39,
          "news": [],
          "chip": {
            "date": "2026-06-17",
            "外資": -459237,
            "投信": 140870,
            "自營": 64862,
            "合計": -253505
          },
          "target_short": 5461.8,
          "target_mid": 4313.8,
          "target_long": 5456.9,
          "atr14": 363.65,
          "stop_loss": 4347.7,
          "broker": null,
          "main_force": null
        },
        {
          "id": "3661",
          "name": "世芯-KY",
          "price": 4320.0,
          "rsi": 57.2,
          "rsi10": 49.1,
          "ret_20d": -6.1,
          "signal": "HOLD",
          "cv_sharpe": -4.88,
          "cv_win_rate": 0.33,
          "news": [],
          "chip": {
            "date": "2026-06-17",
            "外資": -213344,
            "投信": 1967,
            "自營": 31829,
            "合計": -179548
          },
          "target_short": 5004.9,
          "target_mid": 3672.0,
          "target_long": 4716.2,
          "atr14": 261.26,
          "stop_loss": 3797.5,
          "broker": null,
          "main_force": null
        },
        {
          "id": "3529",
          "name": "力旺",
          "price": 3155.0,
          "rsi": 43.0,
          "rsi10": 40.9,
          "ret_20d": -6.8,
          "signal": "HOLD",
          "cv_sharpe": -12.15,
          "cv_win_rate": 0.0,
          "news": [],
          "chip": {
            "date": "2026-06-17",
            "外資": 22806,
            "投信": -25000,
            "自營": -26896,
            "合計": -29090
          },
          "target_short": 3775.0,
          "target_mid": 2681.8,
          "target_long": 3468.3,
          "atr14": 220.13,
          "stop_loss": 2714.7,
          "broker": null,
          "main_force": null
        },
        {
          "id": "6643",
          "name": "M31",
          "price": 482.5,
          "rsi": 36.9,
          "rsi10": 34.9,
          "ret_20d": -14.3,
          "signal": "HOLD",
          "cv_sharpe": -3.68,
          "cv_win_rate": 0.17,
          "news": [],
          "chip": {
            "date": "2026-06-17",
            "外資": -71664,
            "投信": 0,
            "自營": -3472,
            "合計": -75136
          },
          "target_short": 650.8,
          "target_mid": 410.1,
          "target_long": 545.1,
          "atr14": 30.99,
          "stop_loss": 420.5,
          "broker": null,
          "main_force": null
        }
      ],
      "hot_count": 1,
      "buy_count": 0,
      "qualified_count": 1
    },
    "AI 散熱": {
      "avg_ret_20d": 20.33,
      "avg_rsi": 51.4,
      "avg_sharpe": 0.85,
      "stocks": [
        {
          "id": "3017",
          "name": "奇鋐",
          "price": 2365.0,
          "rsi": 30.7,
          "rsi10": 38.6,
          "ret_20d": 1.1,
          "signal": "HOLD",
          "cv_sharpe": 3.04,
          "cv_win_rate": 0.67,
          "news": [],
          "chip": {
            "date": "2026-06-17",
            "外資": 531443,
            "投信": -1292136,
            "自營": 17121,
            "合計": -743572
          },
          "target_short": 2874.4,
          "target_mid": 2315.7,
          "target_long": 2731.0,
          "atr14": 160.05,
          "stop_loss": 2044.9,
          "broker": null,
          "main_force": null
        },
        {
          "id": "3324",
          "name": "雙鴻",
          "price": 1050.0,
          "rsi": 44.3,
          "rsi10": 47.0,
          "ret_20d": 11.8,
          "signal": "SELL",
          "cv_sharpe": -12.14,
          "cv_win_rate": 0.0,
          "news": [],
          "chip": {
            "date": "2026-06-17",
            "外資": -363825,
            "投信": 0,
            "自營": 89741,
            "合計": -274084
          },
          "target_short": 1221.6,
          "target_mid": 1356.7,
          "target_long": 1333.0,
          "atr14": 67.3,
          "stop_loss": 915.4,
          "broker": null,
          "main_force": null
        },
        {
          "id": "3653",
          "name": "健策",
          "price": 3990.0,
          "rsi": 66.7,
          "rsi10": 57.4,
          "ret_20d": 31.7,
          "signal": "HOLD",
          "cv_sharpe": 1.13,
          "cv_win_rate": 0.5,
          "news": [],
          "chip": {
            "date": "2026-06-17",
            "外資": 505715,
            "投信": 128965,
            "自營": -18551,
            "合計": 616129
          },
          "target_short": 4070.3,
          "target_mid": 3391.5,
          "target_long": 4245.5,
          "atr14": 302.99,
          "stop_loss": 3384.0,
          "broker": null,
          "main_force": null
        },
        {
          "id": "8210",
          "name": "勤誠",
          "price": 1345.0,
          "rsi": 33.3,
          "rsi10": 44.1,
          "ret_20d": 4.7,
          "signal": "HOLD",
          "cv_sharpe": 7.1,
          "cv_win_rate": 0.83,
          "news": [],
          "chip": {
            "date": "2026-06-17",
            "外資": 40026,
            "投信": -189000,
            "自營": 5741,
            "合計": -143233
          },
          "target_short": 1504.4,
          "target_mid": 1218.9,
          "target_long": 1487.8,
          "atr14": 93.87,
          "stop_loss": 1157.3,
          "broker": null,
          "main_force": null
        },
        {
          "id": "8996",
          "name": "高力",
          "price": 1515.0,
          "rsi": 82.2,
          "rsi10": 73.1,
          "ret_20d": 52.4,
          "signal": "HOLD",
          "cv_sharpe": 5.11,
          "cv_win_rate": 0.67,
          "news": [],
          "chip": {
            "date": "2026-06-17",
            "外資": 24059,
            "投信": 129745,
            "自營": -100990,
            "合計": 52814
          },
          "target_short": 1421.0,
          "target_mid": 1287.8,
          "target_long": 1587.1,
          "atr14": 108.08,
          "stop_loss": 1298.8,
          "broker": null,
          "main_force": null
        }
      ],
      "hot_count": 1,
      "buy_count": 0,
      "qualified_count": 4
    },
    "AI 電源": {
      "avg_ret_20d": 4.45,
      "avg_rsi": 39.8,
      "avg_sharpe": 5.13,
      "stocks": [
        {
          "id": "2308",
          "name": "台達電",
          "price": 2155.0,
          "rsi": 34.8,
          "rsi10": 43.3,
          "ret_20d": 12.5,
          "signal": "SELL",
          "cv_sharpe": 5.62,
          "cv_win_rate": 0.78,
          "news": [],
          "chip": {
            "date": "2026-06-17",
            "外資": -1912610,
            "投信": -1333027,
            "自營": -107762,
            "合計": -3353399
          },
          "target_short": 2562.9,
          "target_mid": 1831.8,
          "target_long": 2365.9,
          "atr14": 127.79,
          "stop_loss": 1899.4,
          "broker": null,
          "main_force": null
        },
        {
          "id": "2301",
          "name": "光寶科",
          "price": 210.0,
          "rsi": 39.2,
          "rsi10": 44.6,
          "ret_20d": 2.9,
          "signal": "HOLD",
          "cv_sharpe": 8.13,
          "cv_win_rate": 0.67,
          "news": [],
          "chip": {
            "date": "2026-06-17",
            "外資": 258310,
            "投信": -201845,
            "自營": -167521,
            "合計": -111056
          },
          "target_short": 253.9,
          "target_mid": 178.5,
          "target_long": 231.4,
          "atr14": 13.48,
          "stop_loss": 183.0,
          "broker": null,
          "main_force": null
        },
        {
          "id": "6412",
          "name": "群電",
          "price": 92.5,
          "rsi": 45.3,
          "rsi10": 46.0,
          "ret_20d": -2.1,
          "signal": "HOLD",
          "cv_sharpe": 1.64,
          "cv_win_rate": 0.78,
          "news": [],
          "chip": {
            "date": "2026-06-17",
            "外資": -1326395,
            "投信": 10000,
            "自營": 470,
            "合計": -1315925
          },
          "target_short": 109.1,
          "target_mid": 78.6,
          "target_long": 96.9,
          "atr14": 4.96,
          "stop_loss": 82.6,
          "broker": null,
          "main_force": null
        }
      ],
      "hot_count": 0,
      "buy_count": 0,
      "qualified_count": 3
    },
    "被動元件": {
      "avg_ret_20d": 106.6,
      "avg_rsi": 86.2,
      "avg_sharpe": -0.54,
      "stocks": [
        {
          "id": "2327",
          "name": "國巨",
          "price": 984.0,
          "rsi": 88.2,
          "rsi10": 82.2,
          "ret_20d": 89.2,
          "signal": "HOLD",
          "cv_sharpe": 1.1,
          "cv_win_rate": 0.39,
          "news": [],
          "chip": {
            "date": "2026-06-17",
            "外資": -6305815,
            "投信": 2939196,
            "自營": -1355430,
            "合計": -4722049
          },
          "target_short": 996.2,
          "target_mid": 836.4,
          "target_long": 1045.5,
          "atr14": 64.53,
          "stop_loss": 854.9,
          "broker": null,
          "main_force": null
        },
        {
          "id": "2492",
          "name": "華新科",
          "price": 542.0,
          "rsi": 84.1,
          "rsi10": 78.6,
          "ret_20d": 124.0,
          "signal": "HOLD",
          "cv_sharpe": -2.18,
          "cv_win_rate": 0.33,
          "news": [],
          "chip": {
            "date": "2026-06-17",
            "外資": -479462,
            "投信": 20000,
            "自營": 995666,
            "合計": 536204
          },
          "target_short": 530.7,
          "target_mid": 460.7,
          "target_long": 572.3,
          "atr14": 38.55,
          "stop_loss": 464.9,
          "broker": null,
          "main_force": null
        }
      ],
      "hot_count": 2,
      "buy_count": 0,
      "qualified_count": 0
    },
    "小摩AI供應鏈": {
      "avg_ret_20d": 31.22,
      "avg_rsi": 63.8,
      "avg_sharpe": 3.38,
      "stocks": [
        {
          "id": "2327",
          "name": "國巨",
          "price": 984.0,
          "rsi": 88.2,
          "rsi10": 82.2,
          "ret_20d": 89.2,
          "signal": "HOLD",
          "cv_sharpe": 1.1,
          "cv_win_rate": 0.39,
          "news": [],
          "chip": {
            "date": "2026-06-17",
            "外資": -6305815,
            "投信": 2939196,
            "自營": -1355430,
            "合計": -4722049
          },
          "target_short": 996.2,
          "target_mid": 836.4,
          "target_long": 1045.5,
          "atr14": 64.53,
          "stop_loss": 854.9,
          "broker": null,
          "main_force": null
        },
        {
          "id": "2492",
          "name": "華新科",
          "price": 542.0,
          "rsi": 84.1,
          "rsi10": 78.6,
          "ret_20d": 124.0,
          "signal": "HOLD",
          "cv_sharpe": -2.18,
          "cv_win_rate": 0.33,
          "news": [],
          "chip": {
            "date": "2026-06-17",
            "外資": -479462,
            "投信": 20000,
            "自營": 995666,
            "合計": 536204
          },
          "target_short": 530.7,
          "target_mid": 460.7,
          "target_long": 572.3,
          "atr14": 38.55,
          "stop_loss": 464.9,
          "broker": null,
          "main_force": null
        },
        {
          "id": "6510",
          "name": "精測",
          "price": 3540.0,
          "rsi": 56.9,
          "rsi10": 53.4,
          "ret_20d": 4.6,
          "signal": "BUY",
          "cv_sharpe": 5.73,
          "cv_win_rate": 0.72,
          "news": [],
          "chip": {
            "date": "2026-06-17",
            "外資": 51208,
            "投信": 19000,
            "自營": -76856,
            "合計": -6648
          },
          "target_short": 3664.7,
          "target_mid": 3009.0,
          "target_long": 3777.3,
          "atr14": 243.82,
          "stop_loss": 3052.4,
          "broker": null,
          "main_force": null
        },
        {
          "id": "8046",
          "name": "南電",
          "price": 885.0,
          "rsi": 56.7,
          "rsi10": 53.2,
          "ret_20d": 6.8,
          "signal": "SELL",
          "cv_sharpe": 1.28,
          "cv_win_rate": 0.5,
          "news": [],
          "chip": {
            "date": "2026-06-17",
            "外資": -1637366,
            "投信": -2327000,
            "自營": 97141,
            "合計": -3867225
          },
          "target_short": 944.6,
          "target_mid": 924.2,
          "target_long": 1018.8,
          "atr14": 65.32,
          "stop_loss": 754.4,
          "broker": null,
          "main_force": null
        },
        {
          "id": "2383",
          "name": "台光電",
          "price": 5200.0,
          "rsi": 64.9,
          "rsi10": 59.4,
          "ret_20d": 18.3,
          "signal": "BUY",
          "cv_sharpe": 6.34,
          "cv_win_rate": 0.58,
          "news": [],
          "chip": {
            "date": "2026-06-17",
            "外資": 237842,
            "投信": -54289,
            "自營": -71166,
            "合計": 112387
          },
          "target_short": 5430.7,
          "target_mid": 4420.0,
          "target_long": 5558.1,
          "atr14": 329.57,
          "stop_loss": 4540.9,
          "broker": null,
          "main_force": null
        },
        {
          "id": "6213",
          "name": "聯茂",
          "price": 267.5,
          "rsi": 61.9,
          "rsi10": 54.3,
          "ret_20d": 13.1,
          "signal": "HOLD",
          "cv_sharpe": 1.83,
          "cv_win_rate": 0.5,
          "news": [],
          "chip": {
            "date": "2026-06-17",
            "外資": 3070019,
            "投信": 0,
            "自營": 199507,
            "合計": 3269526
          },
          "target_short": 286.8,
          "target_mid": 227.4,
          "target_long": 287.4,
          "atr14": 19.22,
          "stop_loss": 229.1,
          "broker": null,
          "main_force": null
        },
        {
          "id": "2368",
          "name": "金像電",
          "price": 1370.0,
          "rsi": 54.4,
          "rsi10": 52.2,
          "ret_20d": 10.9,
          "signal": "SELL",
          "cv_sharpe": 10.41,
          "cv_win_rate": 0.83,
          "news": [],
          "chip": {
            "date": "2026-06-17",
            "外資": 76666,
            "投信": -70163,
            "自營": 8139,
            "合計": 14642
          },
          "target_short": 1467.1,
          "target_mid": 1164.5,
          "target_long": 1471.6,
          "atr14": 100.67,
          "stop_loss": 1168.7,
          "broker": null,
          "main_force": null
        },
        {
          "id": "6412",
          "name": "群電",
          "price": 92.5,
          "rsi": 45.3,
          "rsi10": 46.0,
          "ret_20d": -2.1,
          "signal": "HOLD",
          "cv_sharpe": 1.64,
          "cv_win_rate": 0.78,
          "news": [],
          "chip": {
            "date": "2026-06-17",
            "外資": -1326395,
            "投信": 10000,
            "自營": 470,
            "合計": -1315925
          },
          "target_short": 109.1,
          "target_mid": 78.6,
          "target_long": 96.9,
          "atr14": 4.96,
          "stop_loss": 82.6,
          "broker": null,
          "main_force": null
        },
        {
          "id": "3105",
          "name": "穩懋",
          "price": 519.0,
          "rsi": 62.2,
          "rsi10": 55.5,
          "ret_20d": 16.2,
          "signal": "HOLD",
          "cv_sharpe": 4.23,
          "cv_win_rate": 0.5,
          "news": [],
          "chip": {
            "date": "2026-06-17",
            "外資": 2602133,
            "投信": -570000,
            "自營": -44709,
            "合計": 1987424
          },
          "target_short": 567.6,
          "target_mid": 641.4,
          "target_long": 640.0,
          "atr14": 40.21,
          "stop_loss": 438.6,
          "broker": null,
          "main_force": null
        }
      ],
      "buy_count": 2,
      "hot_count": 2,
      "qualified_count": 7
    }
  },
  "strong_sectors": [
    "光通訊",
    "記憶體",
    "AI伺服器",
    "封測",
    "光學",
    "IC設計",
    "車用電子",
    "CoPoS封裝",
    "銅箔/CCL",
    "AI 散熱",
    "AI 電源",
    "被動元件"
  ],
  "weak_sectors": [],
  "qualified": [
    {
      "sector": "封測",
      "id": "6510",
      "name": "精測",
      "price": 3540.0,
      "rsi": 56.9,
      "cv_sharpe": 5.73
    },
    {
      "sector": "銅箔/CCL",
      "id": "2383",
      "name": "台光電",
      "price": 5200.0,
      "rsi": 64.9,
      "cv_sharpe": 6.34
    }
  ],
  "alerts": [
    {
      "sector": "記憶體",
      "id": "2408",
      "name": "南亞科",
      "type": "RSI過熱",
      "detail": "RSI=78.1"
    },
    {
      "sector": "記憶體",
      "id": "2344",
      "name": "華邦電",
      "type": "RSI過熱",
      "detail": "RSI=80.6"
    },
    {
      "sector": "光學",
      "id": "3008",
      "name": "大立光",
      "type": "RSI過熱",
      "detail": "RSI=87.2"
    },
    {
      "sector": "IC設計",
      "id": "3034",
      "name": "聯詠",
      "type": "RSI過熱",
      "detail": "RSI=80.7"
    },
    {
      "sector": "IC設計",
      "id": "2379",
      "name": "瑞昱",
      "type": "RSI過熱",
      "detail": "RSI=79.6"
    },
    {
      "sector": "車用電子",
      "id": "2243",
      "name": "怡利電",
      "type": "RSI過熱",
      "detail": "RSI=95.1"
    },
    {
      "sector": "AI ASIC/IP",
      "id": "3443",
      "name": "創意",
      "type": "RSI過熱",
      "detail": "RSI=78.4"
    },
    {
      "sector": "AI 散熱",
      "id": "8996",
      "name": "高力",
      "type": "RSI過熱",
      "detail": "RSI=82.2"
    },
    {
      "sector": "被動元件",
      "id": "2327",
      "name": "國巨",
      "type": "RSI過熱",
      "detail": "RSI=88.2"
    },
    {
      "sector": "被動元件",
      "id": "2492",
      "name": "華新科",
      "type": "RSI過熱",
      "detail": "RSI=84.1"
    }
  ],
  "chart_path": "daily_reports/20260617/01_sector_strength.png",
  "failed_sectors": [],
  "partial_sectors": {
    "被動元件": 1
  },
  "scan_coverage": 100
}