{"meta":{"掃描日期":"20240424","加權指數":null,"漲跌幅%":null,"櫃買指數":"","櫃買漲跌幅%":"","強勢族群":"","弱勢族群":"光通訊, 記憶體, 封測, 光學, IC設計, 車用電子, 綠能環保","雙條件推薦":0,"掃描涵蓋率":100,"失敗族群":[],"部分失敗族群":{}},"qualified":[],"dualFilterExcluded":[],"sectors":[{"sector":"光通訊","ret20":-12.95,"rsi":34.0,"buy":0,"hot":0},{"sector":"記憶體","ret20":-3.21,"rsi":41.4,"buy":1,"hot":0},{"sector":"AI伺服器","ret20":-0.59,"rsi":42.7,"buy":0,"hot":0},{"sector":"封測","ret20":-7.37,"rsi":32.5,"buy":0,"hot":0},{"sector":"光學","ret20":-11.33,"rsi":25.6,"buy":0,"hot":0},{"sector":"IC設計","ret20":-4.27,"rsi":43.8,"buy":0,"hot":0},{"sector":"車用電子","ret20":-10.43,"rsi":32.6,"buy":0,"hot":0},{"sector":"綠能環保","ret20":-10.06,"rsi":37.2,"buy":0,"hot":0},{"sector":"CoPoS封裝","ret20":0.19,"rsi":42.2,"buy":0,"hot":0}],"chips":[],"stocks":[{"date":"20240424","sector":"光通訊","id":"4979","name":"華星光","price":115.0,"rsi":38.5,"rsi10":"","ret20":-20.1,"signal":"HOLD","sharpe":6.19,"foreign":"","trust":"","dealer":"","chipTotal":0,"chip5d":null,"chipDays":null,"chipConc":null,"chipDualBuy":null,"trustDays":null,"chipTier":null,"news":""},{"date":"20240424","sector":"光通訊","id":"3450","name":"聯鈞","price":60.8,"rsi":31.8,"rsi10":"","ret20":-18.9,"signal":"HOLD","sharpe":3.26,"foreign":"","trust":"","dealer":"","chipTotal":0,"chip5d":null,"chipDays":null,"chipConc":null,"chipDualBuy":null,"trustDays":null,"chipTier":null,"news":""},{"date":"20240424","sector":"光通訊","id":"3665","name":"貿聯-KY","price":235.5,"rsi":28.1,"rsi10":"","ret20":-9.6,"signal":"HOLD","sharpe":0.0,"foreign":"","trust":"","dealer":"","chipTotal":0,"chip5d":null,"chipDays":null,"chipConc":null,"chipDualBuy":null,"trustDays":null,"chipTier":null,"news":""},{"date":"20240424","sector":"光通訊","id":"3105","name":"穩懋","price":145.0,"rsi":45.7,"rsi10":"","ret20":-5.5,"signal":"HOLD","sharpe":0.0,"foreign":"","trust":"","dealer":"","chipTotal":0,"chip5d":null,"chipDays":null,"chipConc":null,"chipDualBuy":null,"trustDays":null,"chipTier":null,"news":""},{"date":"20240424","sector":"光通訊","id":"8086","name":"宏捷科","price":133.0,"rsi":31.5,"rsi10":"","ret20":-13.6,"signal":"HOLD","sharpe":2.82,"foreign":"","trust":"","dealer":"","chipTotal":0,"chip5d":null,"chipDays":null,"chipConc":null,"chipDualBuy":null,"trustDays":null,"chipTier":null,"news":""},{"date":"20240424","sector":"光通訊","id":"2455","name":"全新","price":149.5,"rsi":22.6,"rsi10":"","ret20":-16.0,"signal":"HOLD","sharpe":1.59,"foreign":"","trust":"","dealer":"","chipTotal":0,"chip5d":null,"chipDays":null,"chipConc":null,"chipDualBuy":null,"trustDays":null,"chipTier":null,"news":""},{"date":"20240424","sector":"光通訊","id":"4906","name":"正文","price":33.0,"rsi":39.2,"rsi10":"","ret20":-6.5,"signal":"HOLD","sharpe":-5.94,"foreign":"","trust":"","dealer":"","chipTotal":0,"chip5d":null,"chipDays":null,"chipConc":null,"chipDualBuy":null,"trustDays":null,"chipTier":null,"news":""},{"date":"20240424","sector":"光通訊","id":"2345","name":"智邦","price":412.0,"rsi":34.6,"rsi10":"","ret20":-13.3,"signal":"HOLD","sharpe":0.0,"foreign":"","trust":"","dealer":"","chipTotal":0,"chip5d":null,"chipDays":null,"chipConc":null,"chipDualBuy":null,"trustDays":null,"chipTier":null,"news":""},{"date":"20240424","sector":"記憶體","id":"2408","name":"南亞科","price":65.5,"rsi":40.8,"rsi10":"","ret20":-4.4,"signal":"HOLD","sharpe":-1.29,"foreign":"","trust":"","dealer":"","chipTotal":0,"chip5d":null,"chipDays":null,"chipConc":null,"chipDualBuy":null,"trustDays":null,"chipTier":null,"news":""},{"date":"20240424","sector":"記憶體","id":"2337","name":"旺宏","price":26.2,"rsi":32.9,"rsi10":"","ret20":-2.4,"signal":"HOLD","sharpe":0.38,"foreign":"","trust":"","dealer":"","chipTotal":0,"chip5d":null,"chipDays":null,"chipConc":null,"chipDualBuy":null,"trustDays":null,"chipTier":null,"news":""},{"date":"20240424","sector":"記憶體","id":"2344","name":"華邦電","price":25.65,"rsi":38.5,"rsi10":"","ret20":-6.6,"signal":"HOLD","sharpe":-0.87,"foreign":"","trust":"","dealer":"","chipTotal":0,"chip5d":null,"chipDays":null,"chipConc":null,"chipDualBuy":null,"trustDays":null,"chipTier":null,"news":""},{"date":"20240424","sector":"記憶體","id":"3006","name":"晶豪科","price":85.4,"rsi":47.2,"rsi10":"","ret20":-4.0,"signal":"HOLD","sharpe":-4.87,"foreign":"","trust":"","dealer":"","chipTotal":0,"chip5d":null,"chipDays":null,"chipConc":null,"chipDualBuy":null,"trustDays":null,"chipTier":null,"news":""},{"date":"20240424","sector":"記憶體","id":"2451","name":"創見","price":90.4,"rsi":52.2,"rsi10":"","ret20":1.9,"signal":"HOLD","sharpe":1.35,"foreign":"","trust":"","dealer":"","chipTotal":0,"chip5d":null,"chipDays":null,"chipConc":null,"chipDualBuy":null,"trustDays":null,"chipTier":null,"news":""},{"date":"20240424","sector":"記憶體","id":"5289","name":"宜鼎","price":288.0,"rsi":29.8,"rsi10":"","ret20":-6.6,"signal":"HOLD","sharpe":0.0,"foreign":"","trust":"","dealer":"","chipTotal":0,"chip5d":null,"chipDays":null,"chipConc":null,"chipDualBuy":null,"trustDays":null,"chipTier":null,"news":""},{"date":"20240424","sector":"記憶體","id":"3205","name":"十銓","price":42.0,"rsi":48.1,"rsi10":"","ret20":-0.4,"signal":"BUY","sharpe":-5.3,"foreign":"","trust":"","dealer":"","chipTotal":0,"chip5d":null,"chipDays":null,"chipConc":null,"chipDualBuy":null,"trustDays":null,"chipTier":null,"news":""},{"date":"20240424","sector":"AI伺服器","id":"2317","name":"鴻海","price":156.0,"rsi":46.6,"rsi10":"","ret20":7.2,"signal":"HOLD","sharpe":2.85,"foreign":"","trust":"","dealer":"","chipTotal":0,"chip5d":null,"chipDays":null,"chipConc":null,"chipDualBuy":null,"trustDays":null,"chipTier":null,"news":""},{"date":"20240424","sector":"AI伺服器","id":"2382","name":"廣達","price":260.5,"rsi":33.5,"rsi10":"","ret20":2.2,"signal":"HOLD","sharpe":-466.54,"foreign":"","trust":"","dealer":"","chipTotal":0,"chip5d":null,"chipDays":null,"chipConc":null,"chipDualBuy":null,"trustDays":null,"chipTier":null,"news":""},{"date":"20240424","sector":"AI伺服器","id":"3231","name":"緯創","price":115.5,"rsi":39.6,"rsi10":"","ret20":-5.3,"signal":"HOLD","sharpe":4.76,"foreign":"","trust":"","dealer":"","chipTotal":0,"chip5d":null,"chipDays":null,"chipConc":null,"chipDualBuy":null,"trustDays":null,"chipTier":null,"news":""},{"date":"20240424","sector":"AI伺服器","id":"2376","name":"技嘉","price":299.5,"rsi":42.3,"rsi10":"","ret20":-2.1,"signal":"HOLD","sharpe":0.0,"foreign":"","trust":"","dealer":"","chipTotal":0,"chip5d":null,"chipDays":null,"chipConc":null,"chipDualBuy":null,"trustDays":null,"chipTier":null,"news":""},{"date":"20240424","sector":"AI伺服器","id":"4938","name":"和碩","price":96.7,"rsi":45.7,"rsi10":"","ret20":-4.7,"signal":"HOLD","sharpe":-0.35,"foreign":"","trust":"","dealer":"","chipTotal":0,"chip5d":null,"chipDays":null,"chipConc":null,"chipDualBuy":null,"trustDays":null,"chipTier":null,"news":""},{"date":"20240424","sector":"AI伺服器","id":"2357","name":"華碩","price":420.5,"rsi":48.7,"rsi10":"","ret20":-0.7,"signal":"HOLD","sharpe":0.0,"foreign":"","trust":"","dealer":"","chipTotal":0,"chip5d":null,"chipDays":null,"chipConc":null,"chipDualBuy":null,"trustDays":null,"chipTier":null,"news":""},{"date":"20240424","sector":"封測","id":"3711","name":"日月光投控","price":148.0,"rsi":42.3,"rsi10":"","ret20":-6.0,"signal":"HOLD","sharpe":0.0,"foreign":"","trust":"","dealer":"","chipTotal":0,"chip5d":null,"chipDays":null,"chipConc":null,"chipDualBuy":null,"trustDays":null,"chipTier":null,"news":""},{"date":"20240424","sector":"封測","id":"2449","name":"京元電子","price":96.1,"rsi":29.1,"rsi10":"","ret20":-11.4,"signal":"HOLD","sharpe":7.31,"foreign":"","trust":"","dealer":"","chipTotal":0,"chip5d":null,"chipDays":null,"chipConc":null,"chipDualBuy":null,"trustDays":null,"chipTier":null,"news":""},{"date":"20240424","sector":"封測","id":"6510","name":"精測","price":456.0,"rsi":22.0,"rsi10":"","ret20":-11.6,"signal":"HOLD","sharpe":0.0,"foreign":"","trust":"","dealer":"","chipTotal":0,"chip5d":null,"chipDays":null,"chipConc":null,"chipDualBuy":null,"trustDays":null,"chipTier":null,"news":""},{"date":"20240424","sector":"封測","id":"2441","name":"超豐","price":60.5,"rsi":34.8,"rsi10":"","ret20":-4.3,"signal":"HOLD","sharpe":9.66,"foreign":"","trust":"","dealer":"","chipTotal":0,"chip5d":null,"chipDays":null,"chipConc":null,"chipDualBuy":null,"trustDays":null,"chipTier":null,"news":""},{"date":"20240424","sector":"封測","id":"6257","name":"矽格","price":70.4,"rsi":41.7,"rsi10":"","ret20":-2.6,"signal":"HOLD","sharpe":5.87,"foreign":"","trust":"","dealer":"","chipTotal":0,"chip5d":null,"chipDays":null,"chipConc":null,"chipDualBuy":null,"trustDays":null,"chipTier":null,"news":""},{"date":"20240424","sector":"封測","id":"6239","name":"力成","price":173.0,"rsi":25.0,"rsi10":"","ret20":-8.2,"signal":"HOLD","sharpe":7.1,"foreign":"","trust":"","dealer":"","chipTotal":0,"chip5d":null,"chipDays":null,"chipConc":null,"chipDualBuy":null,"trustDays":null,"chipTier":null,"news":""},{"date":"20240424","sector":"光學","id":"3008","name":"大立光","price":2195.0,"rsi":22.4,"rsi10":"","ret20":-10.6,"signal":"HOLD","sharpe":0.0,"foreign":"","trust":"","dealer":"","chipTotal":0,"chip5d":null,"chipDays":null,"chipConc":null,"chipDualBuy":null,"trustDays":null,"chipTier":null,"news":""},{"date":"20240424","sector":"光學","id":"3406","name":"玉晶光","price":433.5,"rsi":28.8,"rsi10":"","ret20":-12.1,"signal":"HOLD","sharpe":0.0,"foreign":"","trust":"","dealer":"","chipTotal":0,"chip5d":null,"chipDays":null,"chipConc":null,"chipDualBuy":null,"trustDays":null,"chipTier":null,"news":""},{"date":"20240424","sector":"IC設計","id":"2454","name":"聯發科","price":1010.0,"rsi":27.4,"rsi10":"","ret20":-9.8,"signal":"HOLD","sharpe":0.0,"foreign":"","trust":"","dealer":"","chipTotal":0,"chip5d":null,"chipDays":null,"chipConc":null,"chipDualBuy":null,"trustDays":null,"chipTier":null,"news":""},{"date":"20240424","sector":"IC設計","id":"3034","name":"聯詠","price":601.0,"rsi":52.1,"rsi10":"","ret20":2.0,"signal":"HOLD","sharpe":0.0,"foreign":"","trust":"","dealer":"","chipTotal":0,"chip5d":null,"chipDays":null,"chipConc":null,"chipDualBuy":null,"trustDays":null,"chipTier":null,"news":""},{"date":"20240424","sector":"IC設計","id":"4966","name":"譜瑞-KY","price":803.0,"rsi":27.8,"rsi10":"","ret20":-17.1,"signal":"HOLD","sharpe":0.0,"foreign":"","trust":"","dealer":"","chipTotal":"","chip5d":null,"chipDays":null,"chipConc":null,"chipDualBuy":null,"trustDays":null,"chipTier":null,"news":""},{"date":"20240424","sector":"IC設計","id":"4919","name":"新唐","price":131.5,"rsi":61.4,"rsi10":"","ret20":6.9,"signal":"HOLD","sharpe":0.0,"foreign":"","trust":"","dealer":"","chipTotal":"","chip5d":null,"chipDays":null,"chipConc":null,"chipDualBuy":null,"trustDays":null,"chipTier":null,"news":""},{"date":"20240424","sector":"IC設計","id":"2388","name":"威盛","price":130.0,"rsi":50.4,"rsi10":"","ret20":-3.3,"signal":"HOLD","sharpe":-1.16,"foreign":"","trust":"","dealer":"","chipTotal":"","chip5d":null,"chipDays":null,"chipConc":null,"chipDualBuy":null,"trustDays":null,"chipTier":null,"news":""},{"date":"20240424","sector":"車用電子","id":"3552","name":"同致","price":106.0,"rsi":23.6,"rsi10":"","ret20":-13.5,"signal":"HOLD","sharpe":0.0,"foreign":"","trust":"","dealer":"","chipTotal":"","chip5d":null,"chipDays":null,"chipConc":null,"chipDualBuy":null,"trustDays":null,"chipTier":null,"news":""},{"date":"20240424","sector":"車用電子","id":"1533","name":"車王電","price":45.45,"rsi":32.9,"rsi10":"","ret20":-7.5,"signal":"HOLD","sharpe":-4.49,"foreign":"","trust":"","dealer":"","chipTotal":"","chip5d":null,"chipDays":null,"chipConc":null,"chipDualBuy":null,"trustDays":null,"chipTier":null,"news":""},{"date":"20240424","sector":"車用電子","id":"2243","name":"怡利電","price":13.95,"rsi":41.2,"rsi10":"","ret20":-10.3,"signal":"HOLD","sharpe":-5.68,"foreign":"","trust":"","dealer":"","chipTotal":"","chip5d":null,"chipDays":null,"chipConc":null,"chipDualBuy":null,"trustDays":null,"chipTier":null,"news":""},{"date":"20240424","sector":"綠能環保","id":"5292","name":"華懋","price":143.0,"rsi":37.2,"rsi10":"","ret20":-10.1,"signal":"HOLD","sharpe":6.71,"foreign":"","trust":"","dealer":"","chipTotal":"","chip5d":null,"chipDays":null,"chipConc":null,"chipDualBuy":null,"trustDays":null,"chipTier":null,"news":""},{"date":"20240424","sector":"CoPoS封裝","id":"6789","name":"采鈺","price":265.0,"rsi":24.9,"rsi10":"","ret20":-16.7,"signal":"HOLD","sharpe":0.0,"foreign":"","trust":"","dealer":"","chipTotal":"","chip5d":null,"chipDays":null,"chipConc":null,"chipDualBuy":null,"trustDays":null,"chipTier":null,"news":""},{"date":"20240424","sector":"CoPoS封裝","id":"3535","name":"晶彩科","price":23.4,"rsi":63.0,"rsi10":"","ret20":14.7,"signal":"HOLD","sharpe":-4.94,"foreign":"","trust":"","dealer":"","chipTotal":"","chip5d":null,"chipDays":null,"chipConc":null,"chipDualBuy":null,"trustDays":null,"chipTier":null,"news":""},{"date":"20240424","sector":"CoPoS封裝","id":"3680","name":"家登","price":442.0,"rsi":42.0,"rsi10":"","ret20":2.7,"signal":"HOLD","sharpe":0.0,"foreign":"","trust":"","dealer":"","chipTotal":"","chip5d":null,"chipDays":null,"chipConc":null,"chipDualBuy":null,"trustDays":null,"chipTier":null,"news":""},{"date":"20240424","sector":"CoPoS封裝","id":"6664","name":"群翊","price":182.0,"rsi":54.7,"rsi10":"","ret20":11.0,"signal":"HOLD","sharpe":3.28,"foreign":"","trust":"","dealer":"","chipTotal":"","chip5d":null,"chipDays":null,"chipConc":null,"chipDualBuy":null,"trustDays":null,"chipTier":null,"news":""},{"date":"20240424","sector":"CoPoS封裝","id":"2467","name":"志聖","price":126.0,"rsi":46.7,"rsi10":"","ret20":-3.8,"signal":"HOLD","sharpe":5.49,"foreign":"","trust":"","dealer":"","chipTotal":"","chip5d":null,"chipDays":null,"chipConc":null,"chipDualBuy":null,"trustDays":null,"chipTier":null,"news":""},{"date":"20240424","sector":"CoPoS封裝","id":"5443","name":"均豪","price":56.4,"rsi":34.5,"rsi10":"","ret20":-0.4,"signal":"HOLD","sharpe":3.25,"foreign":"","trust":"","dealer":"","chipTotal":"","chip5d":null,"chipDays":null,"chipConc":null,"chipDualBuy":null,"trustDays":null,"chipTier":null,"news":""},{"date":"20240424","sector":"CoPoS封裝","id":"6640","name":"均華","price":402.5,"rsi":47.1,"rsi10":"","ret20":-2.9,"signal":"HOLD","sharpe":1.72,"foreign":"","trust":"","dealer":"","chipTotal":"","chip5d":null,"chipDays":null,"chipConc":null,"chipDualBuy":null,"trustDays":null,"chipTier":null,"news":""},{"date":"20240424","sector":"CoPoS封裝","id":"6187","name":"萬潤","price":243.0,"rsi":39.5,"rsi10":"","ret20":-3.2,"signal":"HOLD","sharpe":8.85,"foreign":"","trust":"","dealer":"","chipTotal":"","chip5d":null,"chipDays":null,"chipConc":null,"chipDualBuy":null,"trustDays":null,"chipTier":null,"news":""},{"date":"20240424","sector":"CoPoS封裝","id":"3131","name":"弘塑","price":1045.0,"rsi":54.8,"rsi10":"","ret20":16.6,"signal":"HOLD","sharpe":0.0,"foreign":"","trust":"","dealer":"","chipTotal":"","chip5d":null,"chipDays":null,"chipConc":null,"chipDualBuy":null,"trustDays":null,"chipTier":null,"news":""},{"date":"20240424","sector":"CoPoS封裝","id":"3583","name":"辛耘","price":328.5,"rsi":45.1,"rsi10":"","ret20":10.1,"signal":"HOLD","sharpe":6.34,"foreign":"","trust":"","dealer":"","chipTotal":"","chip5d":null,"chipDays":null,"chipConc":null,"chipDualBuy":null,"trustDays":null,"chipTier":null,"news":""},{"date":"20240424","sector":"CoPoS封裝","id":"3711","name":"日月光投控","price":148.0,"rsi":42.3,"rsi10":"","ret20":-6.0,"signal":"HOLD","sharpe":0.0,"foreign":"","trust":"","dealer":"","chipTotal":0,"chip5d":null,"chipDays":null,"chipConc":null,"chipDualBuy":null,"trustDays":null,"chipTier":null,"news":""},{"date":"20240424","sector":"CoPoS封裝","id":"2449","name":"京元電子","price":96.1,"rsi":29.1,"rsi10":"","ret20":-11.4,"signal":"HOLD","sharpe":7.31,"foreign":"","trust":"","dealer":"","chipTotal":0,"chip5d":null,"chipDays":null,"chipConc":null,"chipDualBuy":null,"trustDays":null,"chipTier":null,"news":""},{"date":"20240424","sector":"CoPoS封裝","id":"6239","name":"力成","price":173.0,"rsi":25.0,"rsi10":"","ret20":-8.2,"signal":"HOLD","sharpe":7.1,"foreign":"","trust":"","dealer":"","chipTotal":0,"chip5d":null,"chipDays":null,"chipConc":null,"chipDualBuy":null,"trustDays":null,"chipTier":null,"news":""}],"mainForce":[],"signalFlips":[{"id":"6257","name":"矽格","sector":"封測","signal_date":"20240418","signal_price":71.5,"price":70.4,"chg_pct":-1.54,"cur_signal":"HOLD","rsi":41.7,"above_ma20":false,"vol_ratio":0.57,"macd_up":false,"status":"轉弱"}],"positions":null}