{"meta":{"掃描日期":"20260316","加權指數":null,"漲跌幅%":null,"櫃買指數":"","櫃買漲跌幅%":"","強勢族群":"光通訊, 記憶體, AI伺服器, IC設計, 車用電子","弱勢族群":"光學, 綠能環保","雙條件推薦":1,"掃描涵蓋率":100,"失敗族群":[],"部分失敗族群":{}},"qualified":[{"sector":"記憶體","id":"2344","name":"華邦電","price":117.0,"rsi":51.2,"cv_sharpe":10.05,"trend_analysis":{"code":"2344","trend_status":"弱勢空頭","ma_alignment":"弱勢空頭，MA5<MA10 但 MA10≥MA20","trend_strength":40,"ma5":208.3,"ma10":208.95,"ma20":188.5,"ma60":135.79,"current_price":207.5,"bias_ma5":-0.38,"bias_ma10":-0.69,"bias_ma20":10.08,"volume_status":"量能正常","volume_ratio_5d":0.95,"volume_trend":"量能正常","support_ma5":false,"support_ma10":false,"buy_signal":"持有","signal_score":79,"signal_reasons":["價格略低於MA5(-0.4%)，回踩買點","RSI強勢(61.8)，多頭力量充足","強勢族群加持，資金輪動有利","CV夏普=10.05（優秀），歷史勝率極佳"],"risk_factors":["死叉，趨勢向下"],"macd_dif":19.3296,"macd_dea":19.7975,"macd_bar":-0.9357,"macd_status":"死叉","macd_signal":"死叉，趨勢向下","rsi_6":56.9,"rsi_12":61.8,"rsi_24":63.2,"rsi_status":"強勢","rsi_signal":"RSI強勢(61.8)，多頭力量充足","sector_is_strong":true,"kd_k":53.64,"kd_d":63.99,"kd_j":32.93,"kd_k_prev":58.12,"kd_d_prev":69.17,"macd_bar_prev":0.22,"entry_strategy":{"vol_ratio":0.87,"vol_ok":false,"macd_momentum":false,"passed":false,"grade":"C"}},"product_mix":{"product_lines":[{"name":"客製化記憶體 (CMS)","share_pct":47,"yoy_growth":265.9,"trend":"up"},{"name":"快閃記憶體 (Flash)","share_pct":32,"yoy_growth":86.2,"trend":"up"},{"name":"邏輯IC (Logic IC)","share_pct":21,"yoy_growth":-5.0,"trend":"down"}],"regions":[],"customers":["全球知名車廠及一階模組廠","AI相關應用客戶 (包含雲端巨頭)","NVIDIA (傳言於2026下半年進入供應鏈)"],"biz_model":"華邦電採整合元件製造商(IDM)模式，從產品設計、技術研發、晶圓製造到自有品牌行銷全球，並提供客製化記憶體解決方案(CMS)，與客戶進行共同開發(JDM)。","moat":"華邦電的核心競爭優勢在於深耕利基型記憶體市場，擁有NOR Flash全球領導地位及SLC NAND市場的強勁需求。其產品組合多元，包括利基型DRAM、NOR Flash、SLC NAND，能有效分散單一產品波動風險，並透過客製化解決方案與客戶建立長期黏著度。公司專注於高階數據中心、AI邊緣運算、車用及工業應用等高門檻領域，並積極布局CUBE先進封裝技術，預計2027年起貢獻顯著營收。此外，華邦電是台灣首家取得車用功能安全最高標準ISO 26262認證的記憶體製造商，並採取選擇性資本支出策略，聚焦具技術優勢的利基產品，以維持穩健的獲利能力。","summary":"華邦電2026年第一季營收受惠於記憶體市場結構性供需失衡及AI應用需求強勁，營收年增91.3%，其中客製化記憶體(CMS)與快閃記憶體(Flash)是主要成長動能，邏輯IC業務則略為下滑。公司持續擴大在車用與工業領域的市佔率，並積極發展CUBE邊緣AI解決方案。最新財報及法說會資料未提供地區別營收分布，但公司業務遍及全球多個國家，產品應用廣泛，顯示其全球化的市場布局。","data_period":"2026年第一季 (1Q26)","updated_at":"2026-06-19"}}],"sectors":[{"sector":"光通訊","ret20":17.82,"rsi":59.8,"buy":2,"hot":0},{"sector":"記憶體","ret20":12.44,"rsi":55.5,"buy":4,"hot":1},{"sector":"AI伺服器","ret20":6.45,"rsi":57.9,"buy":3,"hot":1},{"sector":"封測","ret20":-2.96,"rsi":43.1,"buy":1,"hot":0},{"sector":"光學","ret20":-4.27,"rsi":48.4,"buy":0,"hot":0},{"sector":"IC設計","ret20":6.41,"rsi":52.5,"buy":2,"hot":0},{"sector":"車用電子","ret20":11.81,"rsi":56.7,"buy":1,"hot":1},{"sector":"綠能環保","ret20":-6.04,"rsi":43.7,"buy":0,"hot":0}],"chips":[],"stocks":[{"date":"20260316","sector":"光通訊","id":"4979","name":"華星光","price":427.0,"rsi":61.0,"rsi10":"","ret20":30.2,"signal":"BUY","sharpe":0.87,"foreign":"","trust":"","dealer":"","chipTotal":0,"chip5d":null,"chipDays":null,"chipConc":null,"chipDualBuy":null,"trustDays":null,"chipTier":null,"news":""},{"date":"20260316","sector":"光通訊","id":"3450","name":"聯鈞","price":289.5,"rsi":56.2,"rsi10":"","ret20":10.1,"signal":"SELL","sharpe":2.72,"foreign":"","trust":"","dealer":"","chipTotal":0,"chip5d":null,"chipDays":null,"chipConc":null,"chipDualBuy":null,"trustDays":null,"chipTier":null,"news":""},{"date":"20260316","sector":"光通訊","id":"3665","name":"貿聯-KY","price":1645.0,"rsi":68.4,"rsi10":"","ret20":22.8,"signal":"HOLD","sharpe":6.27,"foreign":"","trust":"","dealer":"","chipTotal":0,"chip5d":null,"chipDays":null,"chipConc":null,"chipDualBuy":null,"trustDays":null,"chipTier":null,"news":""},{"date":"20260316","sector":"光通訊","id":"3105","name":"穩懋","price":303.5,"rsi":58.1,"rsi10":"","ret20":20.7,"signal":"HOLD","sharpe":-0.75,"foreign":"","trust":"","dealer":"","chipTotal":0,"chip5d":null,"chipDays":null,"chipConc":null,"chipDualBuy":null,"trustDays":null,"chipTier":null,"news":""},{"date":"20260316","sector":"光通訊","id":"8086","name":"宏捷科","price":132.5,"rsi":64.8,"rsi10":"","ret20":14.7,"signal":"HOLD","sharpe":-2.34,"foreign":"","trust":"","dealer":"","chipTotal":0,"chip5d":null,"chipDays":null,"chipConc":null,"chipDualBuy":null,"trustDays":null,"chipTier":null,"news":""},{"date":"20260316","sector":"光通訊","id":"2455","name":"全新","price":229.0,"rsi":62.0,"rsi10":"","ret20":26.2,"signal":"HOLD","sharpe":3.02,"foreign":"","trust":"","dealer":"","chipTotal":0,"chip5d":null,"chipDays":null,"chipConc":null,"chipDualBuy":null,"trustDays":null,"chipTier":null,"news":""},{"date":"20260316","sector":"光通訊","id":"4906","name":"正文","price":28.75,"rsi":58.5,"rsi10":"","ret20":0.7,"signal":"HOLD","sharpe":-4.72,"foreign":"","trust":"","dealer":"","chipTotal":0,"chip5d":null,"chipDays":null,"chipConc":null,"chipDualBuy":null,"trustDays":null,"chipTier":null,"news":""},{"date":"20260316","sector":"光通訊","id":"2345","name":"智邦","price":1390.0,"rsi":49.3,"rsi10":"","ret20":17.3,"signal":"HOLD","sharpe":7.55,"foreign":"","trust":"","dealer":"","chipTotal":0,"chip5d":null,"chipDays":null,"chipConc":null,"chipDualBuy":null,"trustDays":null,"chipTier":null,"news":""},{"date":"20260316","sector":"記憶體","id":"2408","name":"南亞科","price":261.5,"rsi":43.9,"rsi10":"","ret20":-11.4,"signal":"HOLD","sharpe":6.2,"foreign":"","trust":"","dealer":"","chipTotal":0,"chip5d":null,"chipDays":null,"chipConc":null,"chipDualBuy":null,"trustDays":null,"chipTier":null,"news":""},{"date":"20260316","sector":"記憶體","id":"2337","name":"旺宏","price":119.0,"rsi":57.9,"rsi10":"","ret20":32.7,"signal":"BUY","sharpe":3.7,"foreign":"","trust":"","dealer":"","chipTotal":0,"chip5d":null,"chipDays":null,"chipConc":null,"chipDualBuy":null,"trustDays":null,"chipTier":null,"news":""},{"date":"20260316","sector":"記憶體","id":"2344","name":"華邦電","price":117.0,"rsi":51.2,"rsi10":"","ret20":7.8,"signal":"BUY","sharpe":7.83,"foreign":"","trust":"","dealer":"","chipTotal":0,"chip5d":null,"chipDays":null,"chipConc":null,"chipDualBuy":null,"trustDays":null,"chipTier":null,"news":""},{"date":"20260316","sector":"記憶體","id":"3006","name":"晶豪科","price":177.0,"rsi":58.7,"rsi10":"","ret20":2.3,"signal":"HOLD","sharpe":-3.76,"foreign":"","trust":"","dealer":"","chipTotal":0,"chip5d":null,"chipDays":null,"chipConc":null,"chipDualBuy":null,"trustDays":null,"chipTier":null,"news":""},{"date":"20260316","sector":"記憶體","id":"2451","name":"創見","price":259.5,"rsi":65.5,"rsi10":"","ret20":13.6,"signal":"BUY","sharpe":5.44,"foreign":"","trust":"","dealer":"","chipTotal":0,"chip5d":null,"chipDays":null,"chipConc":null,"chipDualBuy":null,"trustDays":null,"chipTier":null,"news":""},{"date":"20260316","sector":"記憶體","id":"5289","name":"宜鼎","price":1060.0,"rsi":74.0,"rsi10":"","ret20":36.2,"signal":"HOLD","sharpe":2.06,"foreign":"","trust":"","dealer":"","chipTotal":0,"chip5d":null,"chipDays":null,"chipConc":null,"chipDualBuy":null,"trustDays":null,"chipTier":null,"news":""},{"date":"20260316","sector":"記憶體","id":"3205","name":"十銓","price":50.7,"rsi":37.3,"rsi10":"","ret20":5.8,"signal":"HOLD","sharpe":-0.47,"foreign":"","trust":"","dealer":"","chipTotal":0,"chip5d":null,"chipDays":null,"chipConc":null,"chipDualBuy":null,"trustDays":null,"chipTier":null,"news":""},{"date":"20260316","sector":"AI伺服器","id":"2317","name":"鴻海","price":216.5,"rsi":42.9,"rsi10":"","ret20":-1.1,"signal":"HOLD","sharpe":-3.91,"foreign":"","trust":"","dealer":"","chipTotal":0,"chip5d":null,"chipDays":null,"chipConc":null,"chipDualBuy":null,"trustDays":null,"chipTier":null,"news":""},{"date":"20260316","sector":"AI伺服器","id":"2382","name":"廣達","price":289.0,"rsi":53.7,"rsi10":"","ret20":4.0,"signal":"BUY","sharpe":0.63,"foreign":"","trust":"","dealer":"","chipTotal":0,"chip5d":null,"chipDays":null,"chipConc":null,"chipDualBuy":null,"trustDays":null,"chipTier":null,"news":""},{"date":"20260316","sector":"AI伺服器","id":"3231","name":"緯創","price":135.0,"rsi":57.1,"rsi10":"","ret20":4.7,"signal":"HOLD","sharpe":-3.62,"foreign":"","trust":"","dealer":"","chipTotal":0,"chip5d":null,"chipDays":null,"chipConc":null,"chipDualBuy":null,"trustDays":null,"chipTier":null,"news":""},{"date":"20260316","sector":"AI伺服器","id":"2376","name":"技嘉","price":236.5,"rsi":56.2,"rsi10":"","ret20":3.3,"signal":"HOLD","sharpe":-4.9,"foreign":"","trust":"","dealer":"","chipTotal":0,"chip5d":null,"chipDays":null,"chipConc":null,"chipDualBuy":null,"trustDays":null,"chipTier":null,"news":""},{"date":"20260316","sector":"AI伺服器","id":"4938","name":"和碩","price":77.0,"rsi":63.8,"rsi10":"","ret20":10.6,"signal":"HOLD","sharpe":-4.18,"foreign":"","trust":"","dealer":"","chipTotal":0,"chip5d":null,"chipDays":null,"chipConc":null,"chipDualBuy":null,"trustDays":null,"chipTier":null,"news":""},{"date":"20260316","sector":"AI伺服器","id":"2357","name":"華碩","price":589.0,"rsi":73.5,"rsi10":"","ret20":17.3,"signal":"HOLD","sharpe":4.84,"foreign":"","trust":"","dealer":"","chipTotal":0,"chip5d":null,"chipDays":null,"chipConc":null,"chipDualBuy":null,"trustDays":null,"chipTier":null,"news":""},{"date":"20260316","sector":"封測","id":"3711","name":"日月光投控","price":337.5,"rsi":47.2,"rsi10":"","ret20":11.6,"signal":"SELL","sharpe":-0.02,"foreign":"","trust":"","dealer":"","chipTotal":0,"chip5d":null,"chipDays":null,"chipConc":null,"chipDualBuy":null,"trustDays":null,"chipTier":null,"news":""},{"date":"20260316","sector":"封測","id":"2449","name":"京元電子","price":288.0,"rsi":41.3,"rsi10":"","ret20":-3.0,"signal":"HOLD","sharpe":-0.41,"foreign":"","trust":"","dealer":"","chipTotal":0,"chip5d":null,"chipDays":null,"chipConc":null,"chipDualBuy":null,"trustDays":null,"chipTier":null,"news":""},{"date":"20260316","sector":"封測","id":"6510","name":"精測","price":3735.0,"rsi":47.9,"rsi10":"","ret20":-6.6,"signal":"BUY","sharpe":0.79,"foreign":"","trust":"","dealer":"","chipTotal":0,"chip5d":null,"chipDays":null,"chipConc":null,"chipDualBuy":null,"trustDays":null,"chipTier":null,"news":""},{"date":"20260316","sector":"封測","id":"2441","name":"超豐","price":84.3,"rsi":42.0,"rsi10":"","ret20":-1.6,"signal":"HOLD","sharpe":2.04,"foreign":"","trust":"","dealer":"","chipTotal":0,"chip5d":null,"chipDays":null,"chipConc":null,"chipDualBuy":null,"trustDays":null,"chipTier":null,"news":""},{"date":"20260316","sector":"封測","id":"6257","name":"矽格","price":130.0,"rsi":50.6,"rsi10":"","ret20":1.2,"signal":"HOLD","sharpe":1.16,"foreign":"","trust":"","dealer":"","chipTotal":0,"chip5d":null,"chipDays":null,"chipConc":null,"chipDualBuy":null,"trustDays":null,"chipTier":null,"news":""},{"date":"20260316","sector":"封測","id":"6239","name":"力成","price":204.0,"rsi":29.7,"rsi10":"","ret20":-19.2,"signal":"HOLD","sharpe":5.45,"foreign":"","trust":"","dealer":"","chipTotal":0,"chip5d":null,"chipDays":null,"chipConc":null,"chipDualBuy":null,"trustDays":null,"chipTier":null,"news":""},{"date":"20260316","sector":"光學","id":"3008","name":"大立光","price":2305.0,"rsi":45.7,"rsi10":"","ret20":-2.5,"signal":"HOLD","sharpe":-1.49,"foreign":"","trust":"","dealer":"","chipTotal":0,"chip5d":null,"chipDays":null,"chipConc":null,"chipDualBuy":null,"trustDays":null,"chipTier":null,"news":""},{"date":"20260316","sector":"光學","id":"3406","name":"玉晶光","price":438.5,"rsi":51.0,"rsi10":"","ret20":-6.0,"signal":"HOLD","sharpe":1.45,"foreign":"","trust":"","dealer":"","chipTotal":0,"chip5d":null,"chipDays":null,"chipConc":null,"chipDualBuy":null,"trustDays":null,"chipTier":null,"news":""},{"date":"20260316","sector":"IC設計","id":"2454","name":"聯發科","price":1710.0,"rsi":44.2,"rsi10":"","ret20":-5.0,"signal":"HOLD","sharpe":1.77,"foreign":"","trust":"","dealer":"","chipTotal":0,"chip5d":null,"chipDays":null,"chipConc":null,"chipDualBuy":null,"trustDays":null,"chipTier":null,"news":""},{"date":"20260316","sector":"IC設計","id":"3034","name":"聯詠","price":378.5,"rsi":50.4,"rsi10":"","ret20":3.0,"signal":"HOLD","sharpe":-2.4,"foreign":"","trust":"","dealer":"","chipTotal":0,"chip5d":null,"chipDays":null,"chipConc":null,"chipDualBuy":null,"trustDays":null,"chipTier":null,"news":""},{"date":"20260316","sector":"IC設計","id":"4966","name":"譜瑞-KY","price":520.0,"rsi":51.7,"rsi10":"","ret20":-1.5,"signal":"HOLD","sharpe":-3.85,"foreign":"","trust":"","dealer":"","chipTotal":0,"chip5d":null,"chipDays":null,"chipConc":null,"chipDualBuy":null,"trustDays":null,"chipTier":null,"news":""},{"date":"20260316","sector":"IC設計","id":"4919","name":"新唐","price":84.5,"rsi":69.0,"rsi10":"","ret20":42.0,"signal":"HOLD","sharpe":-4.19,"foreign":"","trust":"","dealer":"","chipTotal":0,"chip5d":null,"chipDays":null,"chipConc":null,"chipDualBuy":null,"trustDays":null,"chipTier":null,"news":""},{"date":"20260316","sector":"IC設計","id":"2388","name":"威盛","price":49.5,"rsi":47.3,"rsi10":"","ret20":-6.4,"signal":"HOLD","sharpe":-6.3,"foreign":"","trust":"","dealer":"","chipTotal":0,"chip5d":null,"chipDays":null,"chipConc":null,"chipDualBuy":null,"trustDays":null,"chipTier":null,"news":""},{"date":"20260316","sector":"車用電子","id":"3552","name":"同致","price":48.25,"rsi":36.5,"rsi10":"","ret20":-11.1,"signal":"HOLD","sharpe":-10.89,"foreign":"","trust":"","dealer":"","chipTotal":0,"chip5d":null,"chipDays":null,"chipConc":null,"chipDualBuy":null,"trustDays":null,"chipTier":null,"news":""},{"date":"20260316","sector":"車用電子","id":"1533","name":"車王電","price":30.9,"rsi":47.6,"rsi10":"","ret20":0.0,"signal":"HOLD","sharpe":-8.58,"foreign":"","trust":"","dealer":"","chipTotal":0,"chip5d":null,"chipDays":null,"chipConc":null,"chipDualBuy":null,"trustDays":null,"chipTier":null,"news":""},{"date":"20260316","sector":"車用電子","id":"2243","name":"怡利電","price":17.15,"rsi":86.1,"rsi10":"","ret20":46.6,"signal":"HOLD","sharpe":5.01,"foreign":"","trust":"","dealer":"","chipTotal":0,"chip5d":null,"chipDays":null,"chipConc":null,"chipDualBuy":null,"trustDays":null,"chipTier":null,"news":""},{"date":"20260316","sector":"綠能環保","id":"5292","name":"華懋","price":179.0,"rsi":43.7,"rsi10":"","ret20":-6.0,"signal":"HOLD","sharpe":2.31,"foreign":"","trust":"","dealer":"","chipTotal":0,"chip5d":null,"chipDays":null,"chipConc":null,"chipDualBuy":null,"trustDays":null,"chipTier":null,"news":""}],"mainForce":[],"signalFlips":[],"positions":null}