[{"id":"4979","name":"華星光","sector":"光通訊"},{"id":"3450","name":"聯鈞","sector":"光通訊"},{"id":"3665","name":"貿聯-KY","sector":"光通訊"},{"id":"3105","name":"穩懋","sector":"光通訊"},{"id":"8086","name":"宏捷科","sector":"光通訊"},{"id":"2455","name":"全新","sector":"光通訊"},{"id":"4906","name":"正文","sector":"光通訊"},{"id":"2345","name":"智邦","sector":"光通訊"},{"id":"2408","name":"南亞科","sector":"記憶體"},{"id":"2337","name":"旺宏","sector":"記憶體"},{"id":"3006","name":"晶豪科","sector":"記憶體"},{"id":"2451","name":"創見","sector":"記憶體"},{"id":"5289","name":"宜鼎","sector":"記憶體"},{"id":"3205","name":"十銓","sector":"記憶體"},{"id":"2317","name":"鴻海","sector":"AI伺服器"},{"id":"2382","name":"廣達","sector":"AI伺服器"},{"id":"3231","name":"緯創","sector":"AI伺服器"},{"id":"2376","name":"技嘉","sector":"AI伺服器"},{"id":"4938","name":"和碩","sector":"AI伺服器"},{"id":"2357","name":"華碩","sector":"AI伺服器"},{"id":"3711","name":"日月光投控","sector":"封測"},{"id":"2449","name":"京元電子","sector":"封測"},{"id":"6510","name":"精測","sector":"封測"},{"id":"2441","name":"超豐","sector":"封測"},{"id":"6257","name":"矽格","sector":"封測"},{"id":"6239","name":"力成","sector":"封測"},{"id":"3008","name":"大立光","sector":"光學"},{"id":"3406","name":"玉晶光","sector":"光學"},{"id":"2454","name":"聯發科","sector":"IC設計"},{"id":"3034","name":"聯詠","sector":"IC設計"},{"id":"4966","name":"譜瑞-KY","sector":"IC設計"},{"id":"4919","name":"新唐","sector":"IC設計"},{"id":"2388","name":"威盛","sector":"IC設計"},{"id":"3552","name":"同致","sector":"車用電子"},{"id":"1533","name":"車王電","sector":"車用電子"},{"id":"2243","name":"怡利電","sector":"車用電子"},{"id":"5292","name":"華懋","sector":"綠能環保"},{"id":"6789","name":"采鈺","sector":"CoPoS封裝"},{"id":"3535","name":"晶彩科","sector":"CoPoS封裝"},{"id":"3680","name":"家登","sector":"CoPoS封裝"},{"id":"6664","name":"群翊","sector":"CoPoS封裝"},{"id":"2467","name":"志聖","sector":"CoPoS封裝"},{"id":"7734","name":"印能","sector":"CoPoS封裝"},{"id":"5443","name":"均豪","sector":"CoPoS封裝"},{"id":"6640","name":"均華","sector":"CoPoS封裝"},{"id":"6187","name":"萬潤","sector":"CoPoS封裝"},{"id":"3131","name":"弘塑","sector":"CoPoS封裝"},{"id":"3583","name":"辛耘","sector":"CoPoS封裝"},{"id":"2344","name":"華邦電","sector":"記憶體"}]