{
  "week_ending": "2026-07-03",
  "days_covered": 5,
  "sector_changes": [
    {
      "sector": "銅箔/CCL",
      "change": 14.79,
      "level": 22.64,
      "prev_change": -0.07
    },
    {
      "sector": "封測",
      "change": 13.71,
      "level": 4.77,
      "prev_change": -23.52
    },
    {
      "sector": "車用電子",
      "change": 12.11,
      "level": 36.35,
      "prev_change": -4.44
    },
    {
      "sector": "CoPoS封裝",
      "change": 9.71,
      "level": 0.17,
      "prev_change": -15.91
    },
    {
      "sector": "ABF載板",
      "change": 9.33,
      "level": 19.9,
      "prev_change": null
    },
    {
      "sector": "AI ASIC/IP",
      "change": 8.76,
      "level": -1.31,
      "prev_change": -1.77
    },
    {
      "sector": "小摩AI供應鏈",
      "change": 7.11,
      "level": 5.9,
      "prev_change": -10.69
    },
    {
      "sector": "綠能環保",
      "change": 7.08,
      "level": 0.89,
      "prev_change": -13.83
    },
    {
      "sector": "被動元件",
      "change": 6.44,
      "level": 42.13,
      "prev_change": -52.5
    },
    {
      "sector": "光通訊",
      "change": 6.08,
      "level": -7.98,
      "prev_change": -13.73
    },
    {
      "sector": "AI 電源",
      "change": 3.41,
      "level": -10.39,
      "prev_change": -18.76
    },
    {
      "sector": "IC設計",
      "change": 0.28,
      "level": 1.38,
      "prev_change": -14.14
    },
    {
      "sector": "AI 散熱",
      "change": -0.59,
      "level": -1.05,
      "prev_change": -8.41
    },
    {
      "sector": "AI伺服器",
      "change": -7.67,
      "level": -13.65,
      "prev_change": -8.62
    },
    {
      "sector": "記憶體",
      "change": -8.08,
      "level": -9.26,
      "prev_change": -17.39
    },
    {
      "sector": "光學",
      "change": -13.23,
      "level": 3.55,
      "prev_change": -10.33
    }
  ],
  "top_buys": [
    {
      "stock": "8150 南茂",
      "buy_days": 3
    },
    {
      "stock": "6271 同欣電",
      "buy_days": 2
    },
    {
      "stock": "5269 祥碩",
      "buy_days": 2
    },
    {
      "stock": "2441 超豐",
      "buy_days": 1
    },
    {
      "stock": "3665 貿聯-KY",
      "buy_days": 1
    },
    {
      "stock": "6640 均華",
      "buy_days": 1
    },
    {
      "stock": "2301 光寶科",
      "buy_days": 1
    }
  ],
  "chart_path": "daily_reports/weekly_20260703/01_weekly_sector_trend.png",
  "narrative": ""
}