{"stock_id": "6239", "name": "力成", "source": "twse_openapi", "revenue": {"month": ["202605"], "revenue": [7917615000], "mom": [null], "yoy": [null], "cum_yoy": [null]}, "eps": {"quarter": ["2026Q1"], "eps": [2.5], "qoq": [null], "yoy": [null]}, "margins": {"quarter": ["2026Q1"], "gross_margin": [19.44], "operating_margin": [12.95], "net_margin": [8.65]}, "meta": {"revenue_months": 24, "financial_quarters": 8, "fetch_errors": [{"field": "revenue", "error": "FinMind API unexpected response: ip banned"}, {"field": "eps_margins", "error": "FinMind API unexpected response: ip banned"}]}, "generated_at": "2026-07-08 12:56", "product_mix": {"product_lines": [{"name": "邏輯晶片 (Logic)", "share_pct": 40, "yoy_growth": null, "trend": "up"}, {"name": "NAND Flash", "share_pct": 25, "yoy_growth": null, "trend": "up"}, {"name": "DRAM", "share_pct": 24, "yoy_growth": null, "trend": "up"}, {"name": "SiP/模組 (SiP/Module)", "share_pct": 11, "yoy_growth": null, "trend": "up"}], "regions": [{"name": "台灣 (Taiwan)", "share_pct": null}, {"name": "新加坡 (Singapore)", "share_pct": null}, {"name": "日本 (Japan)", "share_pct": null}, {"name": "美國 (America)", "share_pct": null}, {"name": "歐洲 (Europe)", "share_pct": null}, {"name": "中國、香港、澳門 (China, Hong Kong, Macao)", "share_pct": null}, {"name": "其他地區 (Other regions)", "share_pct": null}], "customers": ["美光 (Micron)", "SK海力士 (SK Hynix)", "金士頓 (Kingston)", "中國長鑫存儲 (ChangXin Memory)", "NVIDIA", "Intel", "NXP"], "biz_model": "力成作為專業委外封裝測試服務商 (OSAT)，提供晶圓凸塊、針測、IC封裝、最終測試、預燒至成品，以及固態硬碟封裝和系統級封裝 (SiP) 等一站式統包 (Turnkey) 服務，並提供直接出貨 (Drop-shipment) 服務。", "moat": "力成的核心競爭優勢在於其作為全球領先的記憶體封裝測試服務供應商地位，並持續投入先進封裝技術 (如FOPLP、CPO、HBM、2.5D/3D IC整合) 的研發與量產，擁有穩定的品質、精湛的技術，與國際主要半導體客戶建立長期合作關係，以及多元化的產品組合分散風險。", "summary": "力成科技受惠於記憶體市場復甦及AI/HPC需求暢旺，2026年第一季營收與獲利創下近年新高，預期全年營收將實現雙位數成長。公司正積極拓展邏輯晶片業務，特別是在高階封裝領域，並將扇出型面板級封裝 (FOPLP) 作為未來重要的成長動能。目前產品線營收比重以邏輯晶片為大宗，其次為NAND Flash與DRAM，先進封裝業務正逐步提升其貢獻度。", "data_period": "2025 Q3 (產品線營收佔比), 2026 Q1 (營運展望)", "updated_at": "2026-06-23"}}